Workbook
Name _select_from_SELECT_max_sakti_sakti_kode_klp_as_sakti_kode_klp_m_202303280648: migrasiSAwal!$A$1:$P$35
Name _select_from_SELECT_max_sakti_sakti_kode_klp_as_sakti_kode_klp_m_202303280652: selisihMinus!$A$1:$P$1346
Name _select_from_SELECT_max_sakti_sakti_kode_klp_as_sakti_kode_klp_m_202303280655: selisihPlus!$A$1:$P$394
Name _select_from_SELECT_max_sakti_sakti_kode_klp_as_sakti_kode_klp_m_202303280658: selisihNol!$A$1:$P$2634
Name _SELECT_max_sakti_sakti_kode_klp_as_sakti_kode_klp_max_sakti_sak_202303280642: Total!$A$1:$P$4405

Sheet Statistik
B2: URAIAN | C2: SAKTI | F2: SIMRS
C3: Saldo Awal | D3: TakTermigrasi | E3: Saldo Akhir | F3: SaldoAkhir | G3: Pembulatan
B4: TOTAL | C4: =Total!E4406 -> 7084287 | D4: =Total!F4406 -> 40926 | E4: =Total!G4406 -> 3194659 | F4: =Total!I4406 -> 3273671 | G4: =Total!I4406-Total!H4406 -> 57.58
B5: migrasSAwal | C5: =migrasiSAwal!E36 -> 0 | D5: =migrasiSAwal!F36 -> 39687 | E5: =migrasiSAwal!G36 -> 0 | F5: =migrasiSAwal!I36 -> 20235 | G5: =migrasiSAwal!I36-migrasiSAwal!H36 -> 0
B6: selisihMinus | C6: =selisihMinus!E1347 -> 3792854 | D6: =selisihMinus!F1347 -> 789 | E6: =selisihMinus!G1347 -> 2035359 | F6: =selisihMinus!I1347 -> 1467366 | G6: =selisihMinus!I1347-selisihMinus!H1347 -> 44.4
B7: selisihPlus | C7: =selisihPlus!E395 -> 1639516 | D7: =selisihPlus!F395 -> 406 | E7: =selisihPlus!G395 -> 500514 | F7: =selisihPlus!I395 -> 1127284 | G7: =selisihPlus!I395-selisihPlus!H395 -> 13.18
B8: selisihNol (cocok) | C8: =selisihNol!E2635 -> 1651917 | D8: =selisihNol!F2635 -> 44 | E8: =selisihNol!G2635 -> 658786 | F8: =selisihNol!I2635 -> 658786 | G8: =selisihNol!I2635-selisihNol!H2635 -> 0
B9: HITUNG TOTAL | C9: =C5+C6+C7+C8 -> 7084287 | D9: =D5+D6+D7+D8 -> 40926 | E9: =E5+E6+E7+E8 -> 3194659 | F9: =F5+F6+F7+F8 -> 3273671 | G9: =G5+G6+G7+G8 -> 57.58

Sheet Total
A1: sakti_kode_klp | B1: sakti_kode | C1: katalog_grp | D1: sakti_grp | E1: qty_awal | F1: sakti_awal_add | G1: sakti_akhir | H1: simrs_akhir | I1: pembulatan | J1: simrs_trx | K1: selisih_abs | L1: selisih | M1: katalog_kode | N1: katalog_nama | O1: sakti_nama | P1: sakti_nama_klp
A2: 1010401002 | B2: 000478 | C2: 1 | D2: 1 | E2: 17589 | F2: 0 | G2: 5887 | H2: 9490 | I2: 9490 | J2: 3603 | K2: 3603 | L2: 3603 | M2: 10A025 | N2: ADALAT OROS TAB 30 MG | O2: ADALAT OROS TAB 30 MG | P2: OBAT PADAT (PERSEDIAAN LAINNYA)
A3: 1010401002 | B3: 000477 | C3: 1 | D3: 1 | E3: 259 | F3: 0 | G3: 7 | H3: 7 | I3: 7 | J3: 0 | K3: 0 | L3: 0 | M3: 10A044 | N3: ALLORIS TABLET 10 MG | O3: ALLORIS TABLET 10 MG | P3: OBAT PADAT (PERSEDIAAN LAINNYA)
A4: 1010401002 | B4: 000548 | C4: 2 | D4: 2 | E4: 24685 | F4: 0 | G4: 3234 | H4: 1994.67 | I4: 1995 | J4: -1239.33 | K4: 1239.33 | L4: -1239.33 | M4: 10A054 | N4: AMBROXOL 30 mg | O4: AMBROXOL TAB 30MG | P4: OBAT PADAT (PERSEDIAAN LAINNYA)
A5: 1010401002 | B5: 000474 | C5: 1 | D5: 1 | E5: 112934 | F5: 0 | G5: 64 | K5: 64 | L5: -64 | M5: 10A059 | N5: AMLODIPIN TAB 5 MG | O5: AMLODIPIN TAB 5 MG | P5: OBAT PADAT (PERSEDIAAN LAINNYA)
A6: 1010401002 | B6: 000473 | C6: 1 | D6: 1 | E6: 81 | F6: 0 | G6: 0 | K6: 0 | L6: 0 | M6: 10A085 | N6: ARCALION 200 TAB | O6: ARCALION 200 TAB | P6: OBAT PADAT (PERSEDIAAN LAINNYA)
A7: 1010401002 | B7: 000472 | C7: 1 | D7: 1 | E7: 30983 | F7: 0 | G7: 0 | K7: 0 | L7: 0 | M7: 10A095 | N7: ASAM FOLAT 1 MG | O7: ASAM FOLAT 1 MG | P7: OBAT PADAT (PERSEDIAAN LAINNYA)
A8: 1010401002 | B8: 000570 | C8: 1 | D8: 1 | E8: 0 | F8: 0 | G8: 545 | H8: 525 | I8: 525 | J8: -20 | K8: 20 | L8: -20 | M8: 10A097.1 | N8: ARIPIPRAZOLE TAB 5MG | O8: ARIPIPRAZOLE TAB 5MG | P8: OBAT PADAT (PERSEDIAAN LAINNYA)
A9: 1010401002 | B9: 000055 | C9: 1 | D9: 1 | E9: 265 | F9: 0 | G9: 0 | K9: 0 | L9: 0 | M9: 10A098 | N9: ASCARDIA TABLET SALUT ENTERIK 80 MG | O9: ASCARDIA TABLET SALUT ENTERIK 80 MG | P9: OBAT PADAT (PERSEDIAAN LAINNYA)
A10: 1010401002 | B10: 000003 | C10: 1 | D10: 1 | E10: 22 | F10: 0 | G10: 31 | H10: 30 | I10: 30 | J10: -1 | K10: 1 | L10: -1 | M10: 10A105 | N10: ASPILETS 80 MG TAB | O10: ASPILETS 80 MG TAB | P10: OBAT PADAT (PERSEDIAAN LAINNYA)
A11: 1010401002 | B11: 000471 | C11: 1 | D11: 1 | E11: 295 | F11: 0 | G11: 0 | K11: 0 | L11: 0 | M11: 10A112 | N11: ATIVAN TAB 1 MG | O11: ATIVAN TAB 1 MG | P11: OBAT PADAT (PERSEDIAAN LAINNYA)
A12: 1010401002 | B12: 000470 | C12: 1 | D12: 1 | E12: 0 | F12: 0 | G12: 5 | K12: 5 | L12: -5 | M12: 10A128 | N12: ARDIUM TAB 500 MG | O12: ARDIUM TAB 500 MG | P12: OBAT PADAT (PERSEDIAAN LAINNYA)
A13: 1010401002 | B13: 000469 | C13: 1 | D13: 1 | E13: 539 | F13: 0 | G13: 90 | H13: 70 | I13: 70 | J13: -20 | K13: 20 | L13: -20 | M13: 10A161 | N13: ANALSIK | O13: ANALSIK | P13: OBAT PADAT (PERSEDIAAN LAINNYA)
A14: 1010401002 | B14: 000468 | C14: 1 | D14: 1 | E14: 326 | F14: 0 | G14: 20 | H14: 20 | I14: 20 | J14: 0 | K14: 0 | L14: 0 | M14: 10A164 | N14: ARCOXIA TAB 60 MG | O14: ARCOXIA TAB 60 MG | P14: OBAT PADAT (PERSEDIAAN LAINNYA)
A15: 1010401002 | B15: 000467 | C15: 1 | D15: 1 | E15: 107 | F15: 0 | G15: 1 | K15: 1 | L15: -1 | M15: 10A165 | N15: ARCOXIA TAB 90 MG | O15: ARCOXIA TAB 90 MG | P15: OBAT PADAT (PERSEDIAAN LAINNYA)
A16: 1010401002 | B16: 000466 | C16: 1 | D16: 1 | E16: 123 | F16: 0 | G16: 26 | H16: 10 | I16: 10 | J16: -16 | K16: 16 | L16: -16 | M16: 10A166 | N16: ARCOXIA TAB 120 MG | O16: ARCOXIA TAB 120 MG | P16: OBAT PADAT (PERSEDIAAN LAINNYA)
A17: 1010401002 | B17: 000465 | C17: 1 | D17: 1 | E17: 20 | F17: 0 | G17: 0 | K17: 0 | L17: 0 | M17: 10A171 | N17: ABBOTIC XL TAB 500 MG | O17: ABBOTIC XL TAB 500 MG | P17: OBAT PADAT (PERSEDIAAN LAINNYA)
A18: 1010401002 | B18: 000023 | C18: 1 | D18: 1 | E18: 244 | F18: 0 | G18: 0 | K18: 0 | L18: 0 | M18: 10A175 | N18: ABILIFY 10 MG TAB | O18: ABILIFY 10 MG TAB | P18: OBAT PADAT (PERSEDIAAN LAINNYA)
A19: 1010401002 | B19: 000518 | C19: 1 | D19: 1 | E19: 0 | F19: 0 | G19: 0 | K19: 0 | L19: 0 | M19: 10A176 | N19: ABILIFY 15 MG TAB | O19: ABILIFY 15 MG TAB | P19: OBAT PADAT (PERSEDIAAN LAINNYA)
A20: 1010401002 | B20: 000464 | C20: 1 | D20: 1 | E20: 7222 | F20: 0 | G20: 19 | H20: 19 | I20: 19 | J20: 0 | K20: 0 | L20: 0 | M20: 10A177 | N20: AVODART TAB 0.5 MG | O20: AVODART TAB 0.5 MG | P20: OBAT PADAT (PERSEDIAAN LAINNYA)
A21: 1010401002 | B21: 000463 | C21: 1 | D21: 1 | E21: 75 | F21: 0 | G21: 40 | H21: 40 | I21: 40 | J21: 0 | K21: 0 | L21: 0 | M21: 10A185 | N21: ARTRODAR CAP 50 MG | O21: ARTRODAR CAP 50 MG | P21: OBAT PADAT (PERSEDIAAN LAINNYA)
A22: 1010401002 | B22: 000455 | C22: 1 | D22: 1 | E22: 72215 | F22: 0 | G22: 40485 | K22: 40485 | L22: -40485 | M22: 10A191 | N22: ATORVASTATIN TAB 20 MG | O22: ATORVASTATIN TABLET 20 MG | P22: OBAT PADAT (PERSEDIAAN LAINNYA)
A23: 1010401002 | B23: 000462 | C23: 1 | D23: 1 | E23: 447 | F23: 0 | G23: 300 | H23: 285 | I23: 285 | J23: -15 | K23: 15 | L23: -15 | M23: 10A192 | N23: ACPULSIF TAB 5 MG | O23: ACPULSIF TAB 5 MG | P23: OBAT PADAT (PERSEDIAAN LAINNYA)
A24: 1010401002 | B24: 000461 | C24: 1 | D24: 1 | E24: 23 | F24: 0 | G24: 0 | H24: 0 | I24: 0 | J24: 0 | K24: 0 | L24: 0 | M24: 10A200 | N24: AERIUS TAB 5 MG | O24: AERIUS TAB 5 MG | P24: OBAT PADAT (PERSEDIAAN LAINNYA)
A25: 1010401002 | B25: 000571 | C25: 1 | D25: 1 | E25: 0 | F25: 0 | G25: 300 | H25: 300 | I25: 300 | J25: 0 | K25: 0 | L25: 0 | M25: 10A201 | N25: ARIPIPRAZOLE TAB DISPERSIBEL 10MG | O25: ARIPIPRAZOLE TAB DISPERSIBEL 10MG | P25: OBAT PADAT (PERSEDIAAN LAINNYA)
A26: 1010401002 | B26: 000081 | C26: 1 | D26: 1 | E26: 156 | F26: 0 | G26: 37 | H26: 21 | I26: 21 | J26: -16 | K26: 16 | L26: -16 | M26: 10A203 | N26: ALBENDAZOLE TAB 400 MG | O26: ALBENDAZOLE TAB 400 MG | P26: OBAT PADAT (PERSEDIAAN LAINNYA)
A27: 1010401002 | B27: 000460 | C27: 1 | D27: 1 | E27: 75 | F27: 0 | G27: 35 | K27: 35 | L27: -35 | M27: 10A204 | N27: ALERTEN Q25 CAP | O27: ALERTEN Q25 CAP | P27: OBAT PADAT (PERSEDIAAN LAINNYA)
A28: 1010401999 | B28: 003414 | C28: 2 | D28: 2 | E28: 9285 | F28: 0 | G28: 149 | H28: 4 | I28: 4 | J28: -66 | K28: 145 | L28: -145 | M28: 10A249 | N28: AZITROMISIN TABLET 500 MG | O28: AZITROMISIN TABLET 500 MG | P28: OBAT PADAT (PERSEDIAAN LAINNYA)
A29: 1010401999 | B29: 003571 | C29: 1 | D29: 1 | E29: 62017 | F29: 0 | G29: 10412 | H29: 3587.5 | I29: 3588 | J29: -6824.5 | K29: 6824.5 | L29: -6824.5 | M29: 10A250 | N29: ASAM MEFENAMAT 500 MG TABLET | O29: ASAM MEFENAMAT 500 MG TABLET | P29: OBAT LAINNYA (PERSEDIAAN LAINNYA)
A30: 1010401002 | B30: 000457 | C30: 1 | D30: 1 | E30: 47 | F30: 0 | G30: 26 | K30: 26 | L30: -26 | M30: 10A253 | N30: ABIXA 10 MG TAB | O30: ABIXA 10 MG TAB | P30: OBAT PADAT (PERSEDIAAN LAINNYA)
A31: 1010401999 | B31: 000351 | C31: 2 | D31: 2 | E31: 142889 | F31: 0 | G31: 0 | H31: 10279 | I31: 10279 | J31: 10279 | K31: 10279 | L31: 10279 | M31: 10A254 | N31: ACETYLCYSTEIN 200 MG CAPSUL | O31: ACETYLCYSTEIN 200 MG CAPSUL | P31: OBAT PADAT (PERSEDIAAN LAINNYA)
A32: 1010401002 | B32: 000456 | C32: 1 | D32: 1 | E32: 1702 | F32: 0 | G32: 0 | K32: 0 | L32: 0 | M32: 10A255 | N32: ALPENTIN 100 MG CAPS | O32: ALPENTIN 100 MG CAPS | P32: OBAT PADAT (PERSEDIAAN LAINNYA)
A33: 1010401002 | B33: 000454 | C33: 1 | D33: 1 | E33: 23983 | F33: 0 | G33: 11421 | H33: 20516 | I33: 20516 | J33: 9095 | K33: 9095 | L33: 9095 | M33: 10A258 | N33: ACARBOSE TABLET 100 MG | O33: ACARBOSE TABLET 100 MG | P33: OBAT PADAT (PERSEDIAAN LAINNYA)
A34: 1010401002 | B34: 000453 | C34: 1 | D34: 1 | E34: 6364 | F34: 0 | G34: 3709 | H34: 6414 | I34: 6414 | J34: 2705 | K34: 2705 | L34: 2705 | M34: 10A259 | N34: ACARBOSE TAB 50 MG | O34: ACARBOSE TAB 50 MG | P34: OBAT PADAT (PERSEDIAAN LAINNYA)
A35: 1010401002 | B35: 000452 | C35: 1 | D35: 1 | E35: 30738 | F35: 0 | G35: 5686 | H35: 3014 | I35: 3014 | J35: -2037 | K35: 2672 | L35: -2672 | M35: 10A260 | N35: ALLOPURINOL TAB 100 MG | O35: ALLOPURINOL TAB 100 MG | P35: OBAT PADAT (PERSEDIAAN LAINNYA)
A36: 1010401999 | B36: 001047 | C36: 2 | D36: 2 | E36: 90854 | F36: 0 | G36: 3193 | K36: 3193 | L36: -3193 | M36: 10A261 | N36: AMLODIPIN TAB 10 MG | O36: AMLODIPINE TAB 10MG | P36: OBAT PADAT (PERSEDIAAN LAINNYA)
A37: 1010401002 | B37: 000450 | C37: 1 | D37: 1 | E37: 2881 | F37: 0 | G37: 1173 | H37: 663 | I37: 663 | J37: -510 | K37: 510 | L37: -510 | M37: 10A269 | N37: ARICEPT TABLET 10 MG | O37: ARICEPT TABLET 10 MG | P37: OBAT PADAT (PERSEDIAAN LAINNYA)
A38: 1010401002 | B38: 000449 | C38: 1 | D38: 1 | E38: 1188 | F38: 0 | G38: 92 | H38: 4.25 | I38: 5 | J38: -88 | K38: 87.75 | L38: -87.75 | M38: 10A275 | N38: ALPRAZOLAM TABLET 0,5 MG | O38: ALPRAZOLAM TABLET 0,5 MG | P38: OBAT PADAT (PERSEDIAAN LAINNYA)
A39: 1010401002 | B39: 000480 | C39: 2 | D39: 2 | E39: 161 | F39: 0 | G39: 3783 | H39: 2870.99 | I39: 2871 | J39: -912.01 | K39: 912.01 | L39: -912.01 | M39: 10A276 | N39: AMITRIPTILINE TABLET 25 MG | O39: AMITRIPTYLLINE TAB 25 MG | P39: OBAT PADAT (PERSEDIAAN LAINNYA)
A40: 1010401002 | B40: 000538 | C40: 1 | D40: 1 | E40: 0 | F40: 0 | G40: 0 | K40: 0 | L40: 0 | M40: 10A279 | N40: AMOXYCILLIN TAB 500 MG | O40: AMOXYCILLIN TAB 500 MG | P40: OBAT PADAT (PERSEDIAAN LAINNYA)
A41: 1010401002 | B41: 000447 | C41: 1 | D41: 1 | E41: 6 | F41: 0 | G41: 0 | K41: 0 | L41: 0 | M41: 10A281 | N41: ACYCLOVIR 200 MG TAB | O41: ACYCLOVIR 200 MG TAB | P41: OBAT PADAT (PERSEDIAAN LAINNYA)
A42: 1010401002 | B42: 000446 | C42: 1 | D42: 1 | E42: 188 | F42: 0 | G42: 2012 | H42: 1090 | I42: 1090 | J42: -247 | K42: 922 | L42: -922 | M42: 10A282 | N42: ACYCLOVIR 400 MG TAB | O42: ACYCLOVIR 400 MG TAB | P42: OBAT PADAT (PERSEDIAAN LAINNYA)
A43: 1010401999 | B43: 000470 | C43: 2 | D43: 2 | E43: 613 | F43: 0 | G43: 67 | H43: 0 | I43: 0 | J43: -34 | K43: 67 | L43: -67 | M43: 10A285 | N43: AMIODARON TAB 200 MG | O43: KENDARON TAB 200 MG | P43: OBAT PADAT (PERSEDIAAN LAINNYA)
A44: 1010401999 | B44: 003569 | C44: 1 | D44: 1 | E44: 15626 | F44: 0 | G44: 2517 | H44: 1014 | I44: 1014 | J44: -1503 | K44: 1503 | L44: -1503 | M44: 10A289 | N44: ALLOPURINOL TAB 300MG | O44: ALLOPURINOL TAB 300MG | P44: OBAT LAINNYA (PERSEDIAAN LAINNYA)
A45: 1010401999 | B45: 003565 | C45: 2 | D45: 2 | E45: 6409 | F45: 0 | G45: 355 | H45: 680 | I45: 680 | J45: 325 | K45: 325 | L45: 325 | M45: 10A300 | N45: AMOXICILLIN TRIHYDRATE KAPLET 500 MG | O45: AMOXSAN CAP 500 MG | P45: OBAT PADAT (PERSEDIAAN LAINNYA)
A46: 1010401999 | B46: 003563 | C46: 1 | D46: 1 | E46: 334 | F46: 0 | G46: 0 | K46: 0 | L46: 0 | M46: 10A304 | N46: AVIGAN TAB 200 MG | O46: AVIGAN TAB 200 MG | P46: OBAT LAINNYA (PERSEDIAAN LAINNYA)
A47: 1010401999 | B47: 003570 | C47: 2 | D47: 2 | E47: 3436 | F47: 0 | G47: 209 | H47: 58.25 | I47: 59 | J47: -150 | K47: 150.75 | L47: -150.75 | M47: 10A306 | N47: ALPRAZOLAM TAB 1MG | O47: ALPRAZOLAM TABL 1 MG | P47: OBAT LAINNYA (PERSEDIAAN LAINNYA)
A48: 1010401999 | B48: 001245 | C48: 2 | D48: 2 | E48: 1760 | F48: 0 | G48: 231 | H48: 212 | I48: 212 | J48: -19 | K48: 19 | L48: -19 | M48: 10A307 | N48: ANTASIDA TAB | O48: ANTASIDA TAB | P48: OBAT PADAT (PERSEDIAAN LAINNYA)
A49: 1010401999 | B49: 001167 | C49: 1 | D49: 1 | E49: 101 | F49: 0 | G49: 345 | H49: 310 | I49: 310 | J49: -35 | K49: 35 | L49: -35 | M49: 10A311 | N49: ARIPIPRAZOLE TAB DISPERSIBEL 15MG | O49: ARIPIPRAZOLE TAB DISPERSIBEL 15MG | P49: OBAT LAINNYA (PERSEDIAAN LAINNYA)
A50: 1010401999 | B50: 000191 | C50: 1 | D50: 1 | E50: 202000 | F50: 0 | G50: 65950 | H50: 45521 | I50: 45521 | J50: -20375 | K50: 20429 | L50: -20429 | M50: 10A314 | N50: ASAM FOLAT TAB 1MG | O50: ASAM FOLAT TAB 1MG | P50: OBAT LAINNYA (PERSEDIAAN LAINNYA)
A51: 1010401999 | B51: 003619 | C51: 1 | D51: 1 | E51: 0 | F51: 0 | G51: 316 | H51: 247 | I51: 247 | J51: -69 | K51: 69 | L51: -69 | M51: 10A316 | N51: ASAM FOLAT TAB 0,4MG | O51: ASAM FOLAT TAB 0,4MG | P51: OBAT LAINNYA (PERSEDIAAN LAINNYA)
A52: 1010401002 | B52: 000527 | C52: 1 | D52: 1 | E52: 0 | F52: 0 | G52: 0 | K52: 0 | L52: 0 | M52: 10A317 | N52: ABILIFY TAB 5 MG | O52: ABILIFY TAB 5 MG | P52: OBAT PADAT (PERSEDIAAN LAINNYA)
A53: 1010401002 | B53: 000556 | C53: 1 | D53: 1 | E53: 0 | F53: 0 | G53: 852 | H53: 692 | I53: 692 | J53: -160 | K53: 160 | L53: -160 | M53: 10A627 | N53: AMINORAL | O53: AMINORAL | P53: OBAT PADAT (PERSEDIAAN LAINNYA)
A54: 1010401002 | B54: 000444 | C54: 1 | D54: 1 | E54: 160 | F54: 0 | G54: 4 | K54: 4 | L54: -4 | M54: 10B033 | N54: BETABLOK TABLET 100 MG | O54: BETABLOK TABLET 100 MG | P54: OBAT PADAT (PERSEDIAAN LAINNYA)
A55: 1010401002 | B55: 000443 | C55: 1 | D55: 1 | E55: 171 | F55: 0 | G55: 5 | K55: 5 | L55: -5 | M55: 10B035 | N55: BETASERC 8 MG TAB | O55: BETASERC 8 MG TAB | P55: OBAT PADAT (PERSEDIAAN LAINNYA)
A56: 1010401999 | B56: 000353 | C56: 1 | D56: 1 | E56: 294 | F56: 0 | G56: 294 | H56: 294 | I56: 294 | J56: 0 | K56: 0 | L56: 0 | M56: 10B058 | N56: BIOSAN TAB 275 MG | O56: BIOSAN TAB 275 MG | P56: OBAT LAINNYA (PERSEDIAAN LAINNYA)
A57: 1010401002 | B57: 000442 | C57: 1 | D57: 1 | E57: 690 | F57: 0 | G57: 224 | H57: 199 | I57: 199 | J57: -25 | K57: 25 | L57: -25 | M57: 10B065 | N57: BRAXIDIN TAB | O57: BRAXIDIN TAB | P57: OBAT PADAT (PERSEDIAAN LAINNYA)
A58: 1010401002 | B58: 000440 | C58: 1 | D58: 1 | E58: 188 | F58: 0 | G58: 0 | K58: 0 | L58: 0 | M58: 10B079 | N58: BUSCOPAN PLUS TAB | O58: BUSCOPAN PLUS TAB | P58: OBAT PADAT (PERSEDIAAN LAINNYA)
A59: 1010401002 | B59: 000439 | C59: 1 | D59: 1 | E59: 78 | F59: 0 | G59: 0 | K59: 0 | L59: 0 | M59: 10B093 | N59: BETASERC TAB 24 MG | O59: BETASERC TAB 24 MG | P59: OBAT PADAT (PERSEDIAAN LAINNYA)
A60: 1010401999 | B60: 000675 | C60: 1 | D60: 1 | E60: 1385 | F60: 0 | G60: 1002 | H60: 688 | I60: 688 | J60: -314 | K60: 314 | L60: -314 | M60: 10B113 | N60: BETAHISTIN MESILAT TAB 24 MG | O60: BETAHISTIN MESILAT TAB 24 MG | P60: OBAT LAINNYA (PERSEDIAAN LAINNYA)
A61: 1010401002 | B61: 000438 | C61: 1 | D61: 1 | E61: 0 | F61: 0 | G61: 12 | H61: 12 | I61: 12 | J61: 0 | K61: 0 | L61: 0 | M61: 10B117 | N61: BAQUINOR FORTE KAPL 500 MG | O61: BAQUINOR FORTE KAPL 500 MG | P61: OBAT PADAT (PERSEDIAAN LAINNYA)
A62: 1010401002 | B62: 000523 | C62: 1 | D62: 1 | E62: 0 | F62: 0 | G62: 10457 | H62: 7353.25 | I62: 7354 | J62: -3103.75 | K62: 3103.75 | L62: -3103.75 | M62: 10B118 | N62: BAMGETOL FC KAPLET 200 MG | O62: BAMGETOL FC KAPLET 200 MG | P62: OBAT PADAT (PERSEDIAAN LAINNYA)
A63: 1010401002 | B63: 000437 | C63: 1 | D63: 1 | E63: 701 | F63: 0 | G63: 1112 | H63: 917 | I63: 917 | J63: -195 | K63: 195 | L63: -195 | M63: 10B119 | N63: BACTESYN 375 MG | O63: BACTESYN 375 MG | P63: OBAT PADAT (PERSEDIAAN LAINNYA)
A64: 1010401002 | B64: 000436 | C64: 1 | D64: 1 | E64: 2822 | F64: 0 | G64: 679 | H64: 514 | I64: 514 | J64: -165 | K64: 165 | L64: -165 | M64: 10B122 | N64: BIOPREXUM TAB 5 MG | O64: BIOPREXUM TAB 5 MG | P64: OBAT PADAT (PERSEDIAAN LAINNYA)
A65: 1010401999 | B65: 003562 | C65: 1 | D65: 1 | E65: 218 | F65: 0 | G65: 1811 | H65: 1807 | I65: 1807 | J65: -4 | K65: 4 | L65: -4 | M65: 10B131 | N65: BRILINTA FC TAB 90 MG | O65: BRILINTA FC TAB 90 MG | P65: OBAT LAINNYA (PERSEDIAAN LAINNYA)
A66: 1010401999 | B66: 001068 | C66: 2 | D66: 2 | E66: 36185 | F66: 0 | G66: 23959 | H66: 28975 | I66: 28975 | J66: 10865 | K66: 5016 | L66: 5016 | M66: 10B132 | N66: BISOPROLOL TABLET 5 MG | O66: BISOPROLOL TABLET 5 MG | P66: OBAT PADAT (PERSEDIAAN LAINNYA)
A67: 1010401999 | B67: 003560 | C67: 2 | D67: 2 | E67: 6896 | F67: 0 | G67: 776 | H67: 4234 | I67: 4234 | J67: 3378 | K67: 3458 | L67: 3458 | M67: 10B135 | N67: BETAHISTIN MESILAT TABLET 6 MG (DEXA) | O67: BETAHISTIN TABLET 6 MG | P67: OBAT PADAT (PERSEDIAAN LAINNYA)
A68: 1010401999 | B68: 003557 | C68: 3 | D68: 3 | E68: 71338 | F68: 0 | G68: 3643 | H68: 2149 | I68: 2149 | J68: -2413 | K68: 1494 | L68: -1494 | M68: 10B140 | N68: BICARBONAT NATRICUS 500MG TAB | O68: BICARBONAT NATRICUS 500MG TAB | P68: OBAT PADAT (PERSEDIAAN LAINNYA)
A69: 1010401999 | B69: 001166 | C69: 1 | D69: 1 | E69: 38149 | F69: 0 | G69: 7686 | H69: 25625 | I69: 25625 | J69: 18628 | K69: 17939 | L69: 17939 | M69: 10B141 | N69: BISOPROLOL TABLET 2,5MG | O69: BISOPROLOL TABLET 2,5MG | P69: OBAT LAINNYA (PERSEDIAAN LAINNYA)
A70: 1010401999 | B70: 003602 | C70: 2 | D70: 2 | E70: 0 | F70: 0 | G70: 181 | H70: 167 | I70: 167 | J70: -14 | K70: 14 | L70: -14 | M70: 10B142 | N70: BISACODYL TABLET SALUT 5MG | O70: BISAKODIL TABLET 5 mg | P70: OBAT LAINNYA (PERSEDIAAN LAINNYA)
A71: 1010401002 | B71: 000573 | C71: 1 | D71: 1 | E71: 0 | F71: 0 | G71: 9 | H71: 9 | I71: 9 | J71: 0 | K71: 0 | L71: 0 | M71: 10B143 | N71: BETARHIN 10MG TAB | O71: BETARHIN 10MG TAB | P71: OBAT PADAT (PERSEDIAAN LAINNYA)
... A74: 1010401999 | B74: 003554 | C74: 2 | D74: 2 | E74: 301 | F74: 0 | G74: 667 | H74: 305.5 | I74: 306 | J74: -361.5 | K74: 361.5 | L74: -361.5 | M74: 10C001.01 | N74: CEFADROXIL 500 MG | O74: CEFADROXIL KAP 500 MG | P74: OBAT PADAT (PERSEDIAAN LAINNYA)
A75: 1010401999 | B75: 000676 | C75: 1 | D75: 1 | E75: 6718 | F75: 0 | G75: 36 | K75: 36 | L75: -36 | M75: 10C001.010 | N75: CALCITRIOL KAPSUL LUNAK 0,25MG | O75: CALCITRIOL KAPSUL LUNAK 0,25MG | P75: OBAT LAINNYA (PERSEDIAAN LAINNYA)
A76: 1010401999 | B76: 001040 | C76: 1 | D76: 1 | E76: 83161 | F76: 0 | G76: 26915 | H76: 22360 | I76: 22360 | J76: -958 | K76: 4555 | L76: -4555 | M76: 10C001.02 | N76: CLOPIDOGREL TAB 75MG | O76: CLOPIDOGREL TAB 75MG | P76: OBAT LAINNYA (PERSEDIAAN LAINNYA)
A77: 1010401002 | B77: 000434 | C77: 1 | D77: 1 | E77: 3814 | F77: 0 | G77: 13355 | H77: 16022.5 | I77: 16023 | J77: 1187.5 | K77: 2667.5 | L77: 2667.5 | M77: 10C001.023 | N77: CEFIXIME CAP 100 MG | O77: CEFIXIME CAP 100 MG | P77: OBAT PADAT (PERSEDIAAN LAINNYA)
A78: 1010401002 | B78: 000433 | C78: 1 | D78: 1 | E78: 27 | F78: 0 | G78: 4 | H78: 4 | I78: 4 | J78: 0 | K78: 0 | L78: 0 | M78: 10C001.026 | N78: CEFSPAN 200 MG | O78: CEFSPAN 200 MG | P78: OBAT PADAT (PERSEDIAAN LAINNYA)
A79: 1010401002 | B79: 000432 | C79: 1 | D79: 1 | E79: 9 | F79: 0 | G79: 3 | H79: 3 | I79: 3 | J79: 0 | K79: 0 | L79: 0 | M79: 10C001.027 | N79: CEFAT KAPSUL 500 MG | O79: CEFAT KAPSUL 500 MG | P79: OBAT PADAT (PERSEDIAAN LAINNYA)
A80: 1010401002 | B80: 000491 | C80: 1 | D80: 1 | E80: 0 | F80: 0 | G80: 0 | K80: 0 | L80: 0 | M80: 10C001.030 | N80: CELEBREX CAP 200 MG | O80: CELEBREX CAP 200 MG | P80: OBAT PADAT (PERSEDIAAN LAINNYA)
A81: 1010401002 | B81: 000085 | C81: 1 | D81: 1 | E81: 178 | F81: 0 | G81: 64 | H81: 64 | I81: 64 | J81: 0 | K81: 0 | L81: 0 | M81: 10C001.054 | N81: CIPRALEX TAB | O81: CIPRALEX TAB | P81: OBAT PADAT (PERSEDIAAN LAINNYA)
A82: 1010401002 | B82: 000431 | C82: 1 | D82: 1 | E82: 862 | F82: 0 | G82: 2873 | H82: 2002 | I82: 2002 | J82: -871 | K82: 871 | L82: -871 | M82: 10C001.057 | N82: CITAZ 100 MG TAB | O82: CITAZ 100 MG TAB | P82: OBAT PADAT (PERSEDIAAN LAINNYA)
A83: 1010401002 | B83: 000428 | C83: 1 | D83: 1 | E83: 17563 | F83: 0 | G83: 92 | H83: 7 | I83: 7 | J83: -85 | K83: 85 | L83: -85 | M83: 10C001.065 | N83: CLINDAMYCIN CAP 300 MG | O83: CLINDAMYCIN CAP 300 MG | P83: OBAT PADAT (PERSEDIAAN LAINNYA)
A84: 1010401002 | B84: 000427 | C84: 1 | D84: 1 | E84: 774 | F84: 0 | G84: 291 | H84: 269.25 | I84: 270 | J84: -21.75 | K84: 21.75 | L84: -21.75 | M84: 10C001.070 | N84: CHLORPROMAZINE TAB 100 MG | O84: CHLORPROMAZINE TAB 100 MG | P84: OBAT PADAT (PERSEDIAAN LAINNYA)
A85: 1010401002 | B85: 000121 | C85: 1 | D85: 1 | E85: 292 | F85: 0 | G85: 293 | H85: 293 | I85: 293 | J85: 0 | K85: 0 | L85: 0 | M85: 10C001.071 | N85: CODITAM TABLET | O85: CODITAM TABLET | P85: OBAT PADAT (PERSEDIAAN LAINNYA)
A86: 1010401002 | B86: 000426 | C86: 1 | D86: 1 | E86: 225 | F86: 0 | G86: 1571 | H86: 1155 | I86: 1155 | J86: -416 | K86: 416 | L86: -416 | M86: 10C001.076 | N86: CORALAN FC TAB 5 MG | O86: CORALAN FC TAB 5 MG | P86: OBAT PADAT (PERSEDIAAN LAINNYA)
A87: 1010401002 | B87: 000423 | C87: 1 | D87: 1 | E87: 1493 | F87: 0 | G87: 316 | H87: 621 | I87: 621 | J87: 305 | K87: 305 | L87: 305 | M87: 10C001.094 | N87: CRIPSA TAB 2.5 MG | O87: CRIPSA TAB 2.5 MG | P87: OBAT PADAT (PERSEDIAAN LAINNYA)
A88: 1010401002 | B88: 000510 | C88: 1 | D88: 1 | E88: 0 | F88: 0 | G88: 0 | K88: 0 | L88: 0 | M88: 10C001.1.14306 | N88: CYGEST TABLET 200 MG | O88: CYGEST TABLET 200 MG | P88: OBAT PADAT (PERSEDIAAN LAINNYA)
A89: 1010401999 | B89: 001024 | C89: 1 | D89: 1 | E89: 4874 | F89: 0 | G89: 272 | K89: 272 | L89: -272 | M89: 10C001.10 | N89: CALCIUM POLYSTYRENE SULFONATE SERBUK 5G | O89: CALCIUM POLYSTYRENE SULFONATE SERBUK 5G | P89: OBAT LAINNYA (PERSEDIAAN LAINNYA)
A90: 1010401999 | B90: 001046 | C90: 2 | D90: 2 | E90: 14336 | F90: 0 | G90: 2951 | H90: 1141 | I90: 1141 | J90: -1810 | K90: 1810 | L90: -1810 | M90: 10C001.105 | N90: CETIRIZINE TAB 10 MG | O90: CETIRIZINE TAB 10 MG | P90: OBAT PADAT (PERSEDIAAN LAINNYA)
A91: 1010401002 | B91: 000421 | C91: 1 | D91: 1 | E91: 36592 | F91: 0 | G91: 5307 | H91: 1622 | I91: 1622 | J91: -2205 | K91: 3685 | L91: -3685 | M91: 10C001.107 | N91: CEFIXIME CAP 200 MG | O91: CEFIXIME CAP 200 MG | P91: OBAT PADAT (PERSEDIAAN LAINNYA)
A92: 1010401999 | B92: 001595 | C92: 1 | D92: 1 | E92: 100 | F92: 0 | G92: 0 | K92: 0 | L92: 0 | M92: 10C001.11 | N92: CHLORAMEX TAB 500MG | O92: CHLORAMEX TAB 500MG | P92: OBAT LAINNYA (PERSEDIAAN LAINNYA)
A93: 1010401002 | B93: 000420 | C93: 1 | D93: 1 | E93: 27072 | F93: 0 | G93: 5951 | H93: 19728 | I93: 19728 | J93: 13777 | K93: 13777 | L93: 13777 | M93: 10C001.112 | N93: CANDESARTAN CILEXETIL TAB 16 MG | O93: CANDESARTAN CILEXETIL TAB 16 MG | P93: OBAT PADAT (PERSEDIAAN LAINNYA)
A94: 1010401002 | B94: 000419 | C94: 1 | D94: 1 | E94: 14456 | F94: 0 | G94: 5589 | H94: 14338.5 | I94: 14339 | J94: 8749.5 | K94: 8749.5 | L94: 8749.5 | M94: 10C001.113 | N94: CANDESARTAN CILEXETIL TAB 8 MG | O94: CANDESARTAN CILEXETIL TAB 8 MG | P94: OBAT PADAT (PERSEDIAAN LAINNYA)
A95: 1010401002 | B95: 000553 | C95: 1 | D95: 1 | E95: 0 | F95: 0 | G95: 70 | H95: 55 | I95: 55 | J95: -15 | K95: 15 | L95: -15 | M95: 10C001.118 | N95: CARDIO ASPIRIN TAB 100 MG | O95: CARDIO ASPIRIN TAB 100 MG | P95: OBAT PADAT (PERSEDIAAN LAINNYA)
A96: 1010401999 | B96: 003552 | C96: 1 | D96: 1 | E96: 1829 | F96: 0 | G96: 1921 | H96: 1643.12 | I96: 1644 | J96: -277.88 | K96: 277.88 | L96: -277.88 | M96: 10C001.13 | N96: CLOZAPINE TAB 100MG | O96: CLOZAPINE TAB 100MG | P96: OBAT LAINNYA (PERSEDIAAN LAINNYA)
A97: 1010401999 | B97: 003549 | C97: 1 | D97: 1 | E97: 13465 | F97: 0 | G97: 6485 | H97: 2487 | I97: 2487 | J97: -3998 | K97: 3998 | L97: -3998 | M97: 10C001.187 | N97: CONCOR TAB 1,25 MG | O97: CONCOR TAB 1,25 MG | P97: OBAT LAINNYA (PERSEDIAAN LAINNYA)
A98: 1010401999 | B98: 003548 | C98: 1 | D98: 1 | E98: 12 | F98: 0 | G98: 37 | K98: 37 | L98: -37 | M98: 10C001.1872 | N98: CURCUMA SANBE FCT 20 MG | O98: CURCUMA SANBE FCT 20 MG | P98: OBAT LAINNYA (PERSEDIAAN LAINNYA)
A99: 1010401999 | B99: 003547 | C99: 1 | D99: 1 | E99: 4578 | F99: 0 | G99: 4937 | H99: 2946 | I99: 2946 | J99: -1991 | K99: 1991 | L99: -1991 | M99: 10C001.188 | N99: CONCOR TAB 10 MG | O99: CONCOR TAB 10 MG | P99: OBAT LAINNYA (PERSEDIAAN LAINNYA)
A100: 1010401999 | B100: 000195 | C100: 1 | D100: 1 | E100: 0 | F100: 0 | G100: 30 | K100: 30 | L100: -30 | M100: 10C001.21 | N100: CALGAE KAPLET SALUT SELAPUT | O100: CALGAE KAPLET SALUT SELAPUT | P100: OBAT LAINNYA (PERSEDIAAN LAINNYA)
A101: 1010401999 | B101: 003546 | C101: 1 | D101: 1 | E101: 15361 | F101: 0 | G101: 248 | H101: 71 | I101: 71 | J101: -133 | K101: 177 | L101: -177 | M101: 10C001.23 | N101: CAPTOPRIL 50 MG TAB | O101: CAPTOPRIL 50 MG TAB | P101: OBAT LAINNYA (PERSEDIAAN LAINNYA)
A102: 1010401999 | B102: 003550 | C102: 2 | D102: 3 | E102: 4140 | F102: 0 | G102: 6490 | H102: 2695 | I102: 2695 | J102: -783 | K102: 3795 | L102: -3795 | M102: 10C001.25 | N102: CITICOLINE 500MG TABLET | O102: CITICOLINE TAB 500MG | P102: OBAT PADAT (PERSEDIAAN LAINNYA)
...

Sheet migrasiSAwal
A1: sakti_kode_klp | B1: sakti_kode | C1: katalog_grp | D1: sakti_grp | E1: qty_awal | F1: sakti_awal_add | G1: sakti_akhir | H1: simrs_akhir | I1: pembulatan | J1: simrs_trx | K1: selisih_abs | L1: selisih | M1: katalog_kode | N1: katalog_nama | O1: sakti_nama | P1: sakti_nama_klp
C2: 1 | D2: 0 | E2: 0 | F2: 255 | G2: 0 | K2: 0 | L2: 0 | M2: 10F149 | N2: FUROSEMID 40 MG TAB | O2: FUROSEMID 40 MG TAB | P2: Obat Padat(Persediaan Lainnya)
C3: 1 | D3: 0 | E3: 0 | F3: 5 | G3: 0 | K3: 0 | L3: 0 | M3: 10H023.14174 | N3: HERBESSER AMPUL 5 MG / ML 5 ML | O3: HERBESSER AMPUL 5 MG / ML 5 ML | P3: Obat Cair(Persediaan Lainnya)
C4: 1 | D4: 0 | E4: 0 | F4: 18 | G4: 0 | K4: 0 | L4: 0 | M4: 10H079 | N4: HYOSCINE INJ INJEKSI 20MG/ML, AMPUL @ 1 ML | O4: HYOSCINE INJ INJEKSI 20MG/ML, AMPUL @ 1 ML | P4: Obat Cair(Persediaan Lainnya)
C5: 1 | D5: 0 | E5: 0 | F5: 3 | G5: 0 | K5: 0 | L5: 0 | M5: 10W004 | N5: WARFARIN NA TABLET 1 MG | O5: WARFARIN NA TABLET 1 MG | P5: Obat Padat(Persediaan Lainnya)
C6: 1 | D6: 0 | E6: 0 | F6: 31 | G6: 0 | K6: 0 | L6: 0 | M6: 14E003 | N6: EFEPOETIN ALFA 0,6 MG (P) | O6: EFEPOETIN ALFA 0,6 MG (P) | P6: Obat Lainnya(Persediaan Lainnya)
C7: 1 | D7: 0 | E7: 0 | F7: 7 | G7: 0 | K7: 0 | L7: 0 | M7: 14E004 | N7: EFEPOETIN ALFA 1 MG (P) | O7: EFEPOETIN ALFA 1 MG (P) | P7: Obat Lainnya(Persediaan Lainnya)
C8: 1 | D8: 0 | E8: 0 | F8: 130 | G8: 0 | K8: 0 | L8: 0 | M8: 14F014 | N8: FG TROCHES BNPB | O8: FG TROCHES BNPB | P8: Obat Lainnya(Persediaan Lainnya)
C9: 1 | D9: 0 | E9: 0 | F9: 320 | G9: 0 | K9: 0 | L9: 0 | M9: 14H014 | N9: HEMAVITON STAMINA PLUS TAB BNPB | O9: HEMAVITON STAMINA PLUS TAB BNPB | P9: Obat Lainnya(Persediaan Lainnya)
C10: 1 | D10: 0 | E10: 0 | F10: 1 | G10: 0 | K10: 0 | L10: 0 | M10: 14I004 | N10: IMBOOST KIDS REG 60ML BNPB | O10: IMBOOST KIDS REG 60ML BNPB | P10: Obat Lainnya(Persediaan Lainnya)
C11: 1 | D11: 0 | E11: 0 | F11: 84 | G11: 0 | H11: 84 | I11: 84 | J11: 0 | K11: 84 | L11: 84 | M11: 14L012 | N11: LIANHUA QINGWEN CAPSULES @12 TABLET | O11: LIANHUA QINGWEN CAPSULES @12 TABLET | P11: Obat Lainnya(Persediaan Lainnya)
C12: 1 | D12: 0 | E12: 0 | F12: 14 | G12: 0 | K12: 0 | L12: 0 | M12: 14M003 | N12: MIRCERA 50 MCG (P) | O12: MIRCERA 50 MCG (P) | P12: Obat Lainnya(Persediaan Lainnya)
C13: 1 | D13: 0 | E13: 0 | F13: 6850 | G13: 0 | K13: 0 | L13: 0 | M13: 14M014.1 | N13: MULTIVITAMIN & MINERAL (COVID-19) | O13: MULTIVITAMIN & MINERAL (COVID-19) | P13: Obat Lainnya(Persediaan Lainnya)
C14: 1 | D14: 0 | E14: 0 | F14: 6 | G14: 0 | K14: 0 | L14: 0 | M14: 14M019 | N14: MIRCERA 100 MCG (P) | O14: MIRCERA 100 MCG (P) | P14: Obat Lainnya(Persediaan Lainnya)
C15: 1 | D15: 0 | E15: 0 | F15: 19876 | G15: 0 | H15: 15854 | I15: 15854 | J15: -126 | K15: 15854 | L15: 15854 | M15: 14N004 | N15: NORMUDAL 2MG TABLET BNPB | O15: NORMUDAL 2MG TABLET BNPB | P15: Obat Lainnya(Persediaan Lainnya)
C16: 1 | D16: 0 | E16: 0 | F16: 15 | G16: 0 | K16: 0 | L16: 0 | M16: 14N006 | N16: NACL 0,9% 500 ML (P) | O16: NACL 0,9% 500 ML (P) | P16: Obat Lainnya(Persediaan Lainnya)
C17: 1 | D17: 0 | E17: 0 | F17: 16 | G17: 0 | K17: 0 | L17: 0 | M17: 14O004 | N17: OBH COMBI BATUK FLU MADU 100ML BNPB | O17: OBH COMBI BATUK FLU MADU 100ML BNPB | P17: Obat Lainnya(Persediaan Lainnya)
C18: 1 | D18: 0 | E18: 0 | F18: 1 | G18: 0 | H18: 2 | I18: 2 | J18: 0 | K18: 2 | L18: 2 | M18: 14P014 | N18: PAKET DLBS (P) | O18: PAKET DLBS (P) | P18: Obat Lainnya(Persediaan Lainnya)
C19: 1 | D19: 0 | E19: 0 | F19: 204 | G19: 0 | K19: 0 | L19: 0 | M19: 14S005 | N19: SUCRALFATE TABLET 500MG BNPB | O19: SUCRALFATE TABLET 500MG BNPB | P19: Obat Lainnya(Persediaan Lainnya)
C20: 1 | D20: 0 | E20: 0 | F20: 7228 | G20: 0 | H20: 4080 | I20: 4080 | J20: 0 | K20: 4080 | L20: 4080 | M20: 14S006 | N20: SP TROCHES BNPB | O20: SP TROCHES BNPB | P20: Obat Lainnya(Persediaan Lainnya)
C21: 1 | D21: 0 | E21: 0 | F21: 330 | G21: 0 | K21: 0 | L21: 0 | M21: 14S010 | N21: SANGOBION CAPSUL(P) | O21: SANGOBION CAPSUL(P) | P21: Obat Lainnya(Persediaan Lainnya)
C22: 1 | D22: 0 | E22: 0 | F22: 90 | G22: 0 | K22: 0 | L22: 0 | M22: 14V008 | N22: VERMINT CAPSUL BNPB | O22: VERMINT CAPSUL BNPB | P22: Obat Lainnya(Persediaan Lainnya)
C23: 1 | D23: 0 | E23: 0 | F23: 1 | G23: 0 | K23: 0 | L23: 0 | M23: 30K020 | N23: KETOPROFEN SUPP 100 MG | O23: KETOPROFEN SUPP 100 MG | P23: Obat Gel/Salep(Persediaan Lainnya)
C24: 1 | D24: 0 | E24: 0 | F24: 30 | G24: 0 | K24: 0 | L24: 0 | M24: 40E039 | N24: ECOSOL NACL 500 ML (S) | O24: ECOSOL NACL 500 ML (S) | P24: Obat Lainnya(Persediaan Lainnya)
C25: 1 | D25: 0 | E25: 0 | F25: 2 | G25: 0 | K25: 0 | L25: 0 | M25: 40N058 | N25: NEFROFER INJ 100 MG/5 ML | O25: NEFROFER INJ 100 MG/5 ML | P25: Obat Cair(Persediaan Lainnya)
C26: 1 | D26: 0 | E26: 0 | F26: 8 | G26: 0 | H26: 114 | I26: 114 | J26: -9 | K26: 114 | L26: 114 | M26: 80E033.2 | N26: ELECTRODE KHUSUS NEONATUS | O26: ELECTRODE KHUSUS NEONATUS | P26: Alat/Obat Kontrasepsi Keluarga Berencana(Persediaan Lainnya)
C27: 1 | D27: 0 | E27: 0 | F27: 1 | G27: 0 | H27: 1 | I27: 1 | J27: 0 | K27: 1 | L27: 1 | M27: 80K102 | N27: KERTAS CTG / ECG 63 MM X 30 M ALPHA | O27: KERTAS CTG / ECG 63 MM X 30 M ALPHA | P27: Alat/Obat Kontrasepsi Keluarga Berencana(Persediaan Lainnya)
C28: 1 | D28: 0 | E28: 0 | F28: 39 | G28: 0 | K28: 0 | L28: 0 | M28: 80M034.1 | N28: MATA PISAU CARBON STEEL NO 11 | O28: MATA PISAU CARBON STEEL NO 11 | P28: Obat Lainnya(Persediaan Lainnya)
C29: 1 | D29: 0 | E29: 0 | F29: 1 | G29: 0 | K29: 0 | L29: 0 | M29: 80M216 | N29: MASK ANAESTHESIA SIZE 5 | O29: MASK ANAESTHESIA SIZE 5 | P29: Obat Lainnya(Persediaan Lainnya)
C30: 1 | D30: 0 | E30: 0 | F30: 2 | G30: 0 | H30: 0 | I30: 0 | J30: 0 | K30: 0 | L30: 0 | M30: 80M219 | N30: MASK ANAESTHESIA SIZE 3 | O30: MASK ANAESTHESIA SIZE 3 | P30: Obat Lainnya(Persediaan Lainnya)
C31: 1 | D31: 0 | E31: 0 | F31: 91 | G31: 0 | K31: 0 | L31: 0 | M31: 82H003 | N31: HAZMAT COVERALL (APD) ALL SIZE (COVID-19) | O31: HAZMAT COVERALL (APD) ALL SIZE (COVID-19) | P31: Obat Lainnya(Persediaan Lainnya)
C32: 1 | D32: 0 | E32: 0 | F32: 3600 | G32: 0 | K32: 0 | L32: 0 | M32: 82H007 | N32: HANDSCHOEN DISPOSIBLE ALL SIZE (COVID-19) | O32: HANDSCHOEN DISPOSIBLE ALL SIZE (COVID-19) | P32: Obat Lainnya(Persediaan Lainnya)
C33: 1 | D33: 0 | E33: 0 | F33: 22 | G33: 0 | K33: 0 | L33: 0 | M33: 82H010 | N33: HAND SANITIZER (COVID-19) | O33: HAND SANITIZER (COVID-19) | P33: Obat Lainnya(Persediaan Lainnya)
C34: 1 | D34: 0 | E34: 0 | F34: 106 | G34: 0 | H34: 100 | I34: 100 | J34: 0 | K34: 100 | L34: 100 | M34: 82M003 | N34: MASKER N95 (COVID 19) | O34: MASKER N95 (COVID 19) | P34: Obat Lainnya(Persediaan Lainnya)
C35: 1 | D35: 0 | E35: 0 | F35: 300 | G35: 0 | K35: 0 | L35: 0 | M35: 82S006 | N35: SHOE COVER (COVID-19) | O35: SHOE COVER (COVID-19) | P35: Obat Lainnya(Persediaan Lainnya)
E36: =SUM(E2:E35) -> 0 | F36: =SUM(F2:F35) -> 39687 | G36: =SUM(G2:G35) -> 0 | H36: =SUM(H2:H35) -> 20235 | I36: =SUM(I2:I35) -> 20235

Sheet selisihMinus
A1: sakti_kode_klp | B1: sakti_kode | C1: katalog_grp | D1: sakti_grp | E1: qty_awal | F1: sakti_awal_add | G1: sakti_akhir | H1: simrs_akhir | I1: pembulatan | J1: simrs_trx | K1: selisih_abs | L1: selisih | M1: katalog_kode | N1: katalog_nama | O1: sakti_nama | P1: sakti_nama_klp
A2: 1010401002 | B2: 000548 | C2: 2 | D2: 2 | E2: 24685 | F2: 0 | G2: 3234 | H2: 1994.67 | I2: 1995 | J2: -1239.33 | K2: 1239.33 | L2: -1239.33 | M2: 10A054 | N2: AMBROXOL 30 mg | O2: AMBROXOL TAB 30MG | P2: OBAT PADAT (PERSEDIAAN LAINNYA)
A3: 1010401002 | B3: 000474 | C3: 1 | D3: 1 | E3: 112934 | F3: 0 | G3: 64 | K3: 64 | L3: -64 | M3: 10A059 | N3: AMLODIPIN TAB 5 MG | O3: AMLODIPIN TAB 5 MG | P3: OBAT PADAT (PERSEDIAAN LAINNYA)
A4: 1010401002 | B4: 000570 | C4: 1 | D4: 1 | E4: 0 | F4: 0 | G4: 545 | H4: 525 | I4: 525 | J4: -20 | K4: 20 | L4: -20 | M4: 10A097.1 | N4: ARIPIPRAZOLE TAB 5MG | O4: ARIPIPRAZOLE TAB 5MG | P4: OBAT PADAT (PERSEDIAAN LAINNYA)
A5: 1010401002 | B5: 000003 | C5: 1 | D5: 1 | E5: 22 | F5: 0 | G5: 31 | H5: 30 | I5: 30 | J5: -1 | K5: 1 | L5: -1 | M5: 10A105 | N5: ASPILETS 80 MG TAB | O5: ASPILETS 80 MG TAB | P5: OBAT PADAT (PERSEDIAAN LAINNYA)
A6: 1010401002 | B6: 000470 | C6: 1 | D6: 1 | E6: 0 | F6: 0 | G6: 5 | K6: 5 | L6: -5 | M6: 10A128 | N6: ARDIUM TAB 500 MG | O6: ARDIUM TAB 500 MG | P6: OBAT PADAT (PERSEDIAAN LAINNYA)
A7: 1010401002 | B7: 000469 | C7: 1 | D7: 1 | E7: 539 | F7: 0 | G7: 90 | H7: 70 | I7: 70 | J7: -20 | K7: 20 | L7: -20 | M7: 10A161 | N7: ANALSIK | O7: ANALSIK | P7: OBAT PADAT (PERSEDIAAN LAINNYA)
A8: 1010401002 | B8: 000467 | C8: 1 | D8: 1 | E8: 107 | F8: 0 | G8: 1 | K8: 1 | L8: -1 | M8: 10A165 | N8: ARCOXIA TAB 90 MG | O8: ARCOXIA TAB 90 MG | P8: OBAT PADAT (PERSEDIAAN LAINNYA)
A9: 1010401002 | B9: 000466 | C9: 1 | D9: 1 | E9: 123 | F9: 0 | G9: 26 | H9: 10 | I9: 10 | J9: -16 | K9: 16 | L9: -16 | M9: 10A166 | N9: ARCOXIA TAB 120 MG | O9: ARCOXIA TAB 120 MG | P9: OBAT PADAT (PERSEDIAAN LAINNYA)
A10: 1010401002 | B10: 000455 | C10: 1 | D10: 1 | E10: 72215 | F10: 0 | G10: 40485 | K10: 40485 | L10: -40485 | M10: 10A191 | N10: ATORVASTATIN TAB 20 MG | O10: ATORVASTATIN TABLET 20 MG | P10: OBAT PADAT (PERSEDIAAN LAINNYA)
A11: 1010401002 | B11: 000462 | C11: 1 | D11: 1 | E11: 447 | F11: 0 | G11: 300 | H11: 285 | I11: 285 | J11: -15 | K11: 15 | L11: -15 | M11: 10A192 | N11: ACPULSIF TAB 5 MG | O11: ACPULSIF TAB 5 MG | P11: OBAT PADAT (PERSEDIAAN LAINNYA)
A12: 1010401002 | B12: 000081 | C12: 1 | D12: 1 | E12: 156 | F12: 0 | G12: 37 | H12: 21 | I12: 21 | J12: -16 | K12: 16 | L12: -16 | M12: 10A203 | N12: ALBENDAZOLE TAB 400 MG | O12: ALBENDAZOLE TAB 400 MG | P12: OBAT PADAT (PERSEDIAAN LAINNYA)
A13: 1010401002 | B13: 000460 | C13: 1 | D13: 1 | E13: 75 | F13: 0 | G13: 35 | K13: 35 | L13: -35 | M13: 10A204 | N13: ALERTEN Q25 CAP | O13: ALERTEN Q25 CAP | P13: OBAT PADAT (PERSEDIAAN LAINNYA)
A14: 1010401999 | B14: 003414 | C14: 2 | D14: 2 | E14: 9285 | F14: 0 | G14: 149 | H14: 4 | I14: 4 | J14: -66 | K14: 145 | L14: -145 | M14: 10A249 | N14: AZITROMISIN TABLET 500 MG | O14: AZITROMISIN TABLET 500 MG | P14: OBAT PADAT (PERSEDIAAN LAINNYA)
A15: 1010401999 | B15: 003571 | C15: 1 | D15: 1 | E15: 62017 | F15: 0 | G15: 10412 | H15: 3587.5 | I15: 3588 | J15: -6824.5 | K15: 6824.5 | L15: -6824.5 | M15: 10A250 | N15: ASAM MEFENAMAT 500 MG TABLET | O15: ASAM MEFENAMAT 500 MG TABLET | P15: OBAT LAINNYA (PERSEDIAAN LAINNYA)
A16: 1010401002 | B16: 000457 | C16: 1 | D16: 1 | E16: 47 | F16: 0 | G16: 26 | K16: 26 | L16: -26 | M16: 10A253 | N16: ABIXA 10 MG TAB | O16: ABIXA 10 MG TAB | P16: OBAT PADAT (PERSEDIAAN LAINNYA)
A17: 1010401002 | B17: 000452 | C17: 1 | D17: 1 | E17: 30738 | F17: 0 | G17: 5686 | H17: 3014 | I17: 3014 | J17: -2037 | K17: 2672 | L17: -2672 | M17: 10A260 | N17: ALLOPURINOL TAB 100 MG | O17: ALLOPURINOL TAB 100 MG | P17: OBAT PADAT (PERSEDIAAN LAINNYA)
A18: 1010401999 | B18: 001047 | C18: 2 | D18: 2 | E18: 90854 | F18: 0 | G18: 3193 | K18: 3193 | L18: -3193 | M18: 10A261 | N18: AMLODIPIN TAB 10 MG | O18: AMLODIPINE TAB 10MG | P18: OBAT PADAT (PERSEDIAAN LAINNYA)
A19: 1010401002 | B19: 000450 | C19: 1 | D19: 1 | E19: 2881 | F19: 0 | G19: 1173 | H19: 663 | I19: 663 | J19: -510 | K19: 510 | L19: -510 | M19: 10A269 | N19: ARICEPT TABLET 10 MG | O19: ARICEPT TABLET 10 MG | P19: OBAT PADAT (PERSEDIAAN LAINNYA)
A20: 1010401002 | B20: 000449 | C20: 1 | D20: 1 | E20: 1188 | F20: 0 | G20: 92 | H20: 4.25 | I20: 5 | J20: -88 | K20: 87.75 | L20: -87.75 | M20: 10A275 | N20: ALPRAZOLAM TABLET 0,5 MG | O20: ALPRAZOLAM TABLET 0,5 MG | P20: OBAT PADAT (PERSEDIAAN LAINNYA)
A21: 1010401002 | B21: 000480 | C21: 2 | D21: 2 | E21: 161 | F21: 0 | G21: 3783 | H21: 2870.99 | I21: 2871 | J21: -912.01 | K21: 912.01 | L21: -912.01 | M21: 10A276 | N21: AMITRIPTILINE TABLET 25 MG | O21: AMITRIPTYLLINE TAB 25 MG | P21: OBAT PADAT (PERSEDIAAN LAINNYA)
A22: 1010401002 | B22: 000446 | C22: 1 | D22: 1 | E22: 188 | F22: 0 | G22: 2012 | H22: 1090 | I22: 1090 | J22: -247 | K22: 922 | L22: -922 | M22: 10A282 | N22: ACYCLOVIR 400 MG TAB | O22: ACYCLOVIR 400 MG TAB | P22: OBAT PADAT (PERSEDIAAN LAINNYA)
A23: 1010401999 | B23: 000470 | C23: 2 | D23: 2 | E23: 613 | F23: 0 | G23: 67 | H23: 0 | I23: 0 | J23: -34 | K23: 67 | L23: -67 | M23: 10A285 | N23: AMIODARON TAB 200 MG | O23: KENDARON TAB 200 MG | P23: OBAT PADAT (PERSEDIAAN LAINNYA)
A24: 1010401999 | B24: 003569 | C24: 1 | D24: 1 | E24: 15626 | F24: 0 | G24: 2517 | H24: 1014 | I24: 1014 | J24: -1503 | K24: 1503 | L24: -1503 | M24: 10A289 | N24: ALLOPURINOL TAB 300MG | O24: ALLOPURINOL TAB 300MG | P24: OBAT LAINNYA (PERSEDIAAN LAINNYA)
A25: 1010401999 | B25: 003570 | C25: 2 | D25: 2 | E25: 3436 | F25: 0 | G25: 209 | H25: 58.25 | I25: 59 | J25: -150 | K25: 150.75 | L25: -150.75 | M25: 10A306 | N25: ALPRAZOLAM TAB 1MG | O25: ALPRAZOLAM TABL 1 MG | P25: OBAT LAINNYA (PERSEDIAAN LAINNYA)
A26: 1010401999 | B26: 001245 | C26: 2 | D26: 2 | E26: 1760 | F26: 0 | G26: 231 | H26: 212 | I26: 212 | J26: -19 | K26: 19 | L26: -19 | M26: 10A307 | N26: ANTASIDA TAB | O26: ANTASIDA TAB | P26: OBAT PADAT (PERSEDIAAN LAINNYA)
A27: 1010401999 | B27: 001167 | C27: 1 | D27: 1 | E27: 101 | F27: 0 | G27: 345 | H27: 310 | I27: 310 | J27: -35 | K27: 35 | L27: -35 | M27: 10A311 | N27: ARIPIPRAZOLE TAB DISPERSIBEL 15MG | O27: ARIPIPRAZOLE TAB DISPERSIBEL 15MG | P27: OBAT LAINNYA (PERSEDIAAN LAINNYA)
A28: 1010401999 | B28: 000191 | C28: 1 | D28: 1 | E28: 202000 | F28: 0 | G28: 65950 | H28: 45521 | I28: 45521 | J28: -20375 | K28: 20429 | L28: -20429 | M28: 10A314 | N28: ASAM FOLAT TAB 1MG | O28: ASAM FOLAT TAB 1MG | P28: OBAT LAINNYA (PERSEDIAAN LAINNYA)
A29: 1010401999 | B29: 003619 | C29: 1 | D29: 1 | E29: 0 | F29: 0 | G29: 316 | H29: 247 | I29: 247 | J29: -69 | K29: 69 | L29: -69 | M29: 10A316 | N29: ASAM FOLAT TAB 0,4MG | O29: ASAM FOLAT TAB 0,4MG | P29: OBAT LAINNYA (PERSEDIAAN LAINNYA)
A30: 1010401002 | B30: 000556 | C30: 1 | D30: 1 | E30: 0 | F30: 0 | G30: 852 | H30: 692 | I30: 692 | J30: -160 | K30: 160 | L30: -160 | M30: 10A627 | N30: AMINORAL | O30: AMINORAL | P30: OBAT PADAT (PERSEDIAAN LAINNYA)
A31: 1010401002 | B31: 000444 | C31: 1 | D31: 1 | E31: 160 | F31: 0 | G31: 4 | K31: 4 | L31: -4 | M31: 10B033 | N31: BETABLOK TABLET 100 MG | O31: BETABLOK TABLET 100 MG | P31: OBAT PADAT (PERSEDIAAN LAINNYA)
A32: 1010401002 | B32: 000443 | C32: 1 | D32: 1 | E32: 171 | F32: 0 | G32: 5 | K32: 5 | L32: -5 | M32: 10B035 | N32: BETASERC 8 MG TAB | O32: BETASERC 8 MG TAB | P32: OBAT PADAT (PERSEDIAAN LAINNYA)
A33: 1010401002 | B33: 000442 | C33: 1 | D33: 1 | E33: 690 | F33: 0 | G33: 224 | H33: 199 | I33: 199 | J33: -25 | K33: 25 | L33: -25 | M33: 10B065 | N33: BRAXIDIN TAB | O33: BRAXIDIN TAB | P33: OBAT PADAT (PERSEDIAAN LAINNYA)
A34: 1010401999 | B34: 000675 | C34: 1 | D34: 1 | E34: 1385 | F34: 0 | G34: 1002 | H34: 688 | I34: 688 | J34: -314 | K34: 314 | L34: -314 | M34: 10B113 | N34: BETAHISTIN MESILAT TAB 24 MG | O34: BETAHISTIN MESILAT TAB 24 MG | P34: OBAT LAINNYA (PERSEDIAAN LAINNYA)
A35: 1010401002 | B35: 000523 | C35: 1 | D35: 1 | E35: 0 | F35: 0 | G35: 10457 | H35: 7353.25 | I35: 7354 | J35: -3103.75 | K35: 3103.75 | L35: -3103.75 | M35: 10B118 | N35: BAMGETOL FC KAPLET 200 MG | O35: BAMGETOL FC KAPLET 200 MG | P35: OBAT PADAT (PERSEDIAAN LAINNYA)
A36: 1010401002 | B36: 000437 | C36: 1 | D36: 1 | E36: 701 | F36: 0 | G36: 1112 | H36: 917 | I36: 917 | J36: -195 | K36: 195 | L36: -195 | M36: 10B119 | N36: BACTESYN 375 MG | O36: BACTESYN 375 MG | P36: OBAT PADAT (PERSEDIAAN LAINNYA)
A37: 1010401002 | B37: 000436 | C37: 1 | D37: 1 | E37: 2822 | F37: 0 | G37: 679 | H37: 514 | I37: 514 | J37: -165 | K37: 165 | L37: -165 | M37: 10B122 | N37: BIOPREXUM TAB 5 MG | O37: BIOPREXUM TAB 5 MG | P37: OBAT PADAT (PERSEDIAAN LAINNYA)
A38: 1010401999 | B38: 003562 | C38: 1 | D38: 1 | E38: 218 | F38: 0 | G38: 1811 | H38: 1807 | I38: 1807 | J38: -4 | K38: 4 | L38: -4 | M38: 10B131 | N38: BRILINTA FC TAB 90 MG | O38: BRILINTA FC TAB 90 MG | P38: OBAT LAINNYA (PERSEDIAAN LAINNYA)
A39: 1010401999 | B39: 003557 | C39: 3 | D39: 3 | E39: 71338 | F39: 0 | G39: 3643 | H39: 2149 | I39: 2149 | J39: -2413 | K39: 1494 | L39: -1494 | M39: 10B140 | N39: BICARBONAT NATRICUS 500MG TAB | O39: BICARBONAT NATRICUS 500MG TAB | P39: OBAT PADAT (PERSEDIAAN LAINNYA)
A40: 1010401999 | B40: 003602 | C40: 2 | D40: 2 | E40: 0 | F40: 0 | G40: 181 | H40: 167 | I40: 167 | J40: -14 | K40: 14 | L40: -14 | M40: 10B142 | N40: BISACODYL TABLET SALUT 5MG | O40: BISAKODIL TABLET 5 mg | P40: OBAT LAINNYA (PERSEDIAAN LAINNYA)
A41: 1010401999 | B41: 003554 | C41: 2 | D41: 2 | E41: 301 | F41: 0 | G41: 667 | H41: 305.5 | I41: 306 | J41: -361.5 | K41: 361.5 | L41: -361.5 | M41: 10C001.01 | N41: CEFADROXIL 500 MG | O41: CEFADROXIL KAP 500 MG | P41: OBAT PADAT (PERSEDIAAN LAINNYA)
A42: 1010401999 | B42: 000676 | C42: 1 | D42: 1 | E42: 6718 | F42: 0 | G42: 36 | K42: 36 | L42: -36 | M42: 10C001.010 | N42: CALCITRIOL KAPSUL LUNAK 0,25MG | O42: CALCITRIOL KAPSUL LUNAK 0,25MG | P42: OBAT LAINNYA (PERSEDIAAN LAINNYA)
A43: 1010401999 | B43: 001040 | C43: 1 | D43: 1 | E43: 83161 | F43: 0 | G43: 26915 | H43: 22360 | I43: 22360 | J43: -958 | K43: 4555 | L43: -4555 | M43: 10C001.02 | N43: CLOPIDOGREL TAB 75MG | O43: CLOPIDOGREL TAB 75MG | P43: OBAT LAINNYA (PERSEDIAAN LAINNYA)
A44: 1010401002 | B44: 000431 | C44: 1 | D44: 1 | E44: 862 | F44: 0 | G44: 2873 | H44: 2002 | I44: 2002 | J44: -871 | K44: 871 | L44: -871 | M44: 10C001.057 | N44: CITAZ 100 MG TAB | O44: CITAZ 100 MG TAB | P44: OBAT PADAT (PERSEDIAAN LAINNYA)
A45: 1010401002 | B45: 000428 | C45: 1 | D45: 1 | E45: 17563 | F45: 0 | G45: 92 | H45: 7 | I45: 7 | J45: -85 | K45: 85 | L45: -85 | M45: 10C001.065 | N45: CLINDAMYCIN CAP 300 MG | O45: CLINDAMYCIN CAP 300 MG | P45: OBAT PADAT (PERSEDIAAN LAINNYA)
A46: 1010401002 | B46: 000427 | C46: 1 | D46: 1 | E46: 774 | F46: 0 | G46: 291 | H46: 269.25 | I46: 270 | J46: -21.75 | K46: 21.75 | L46: -21.75 | M46: 10C001.070 | N46: CHLORPROMAZINE TAB 100 MG | O46: CHLORPROMAZINE TAB 100 MG | P46: OBAT PADAT (PERSEDIAAN LAINNYA)
A47: 1010401002 | B47: 000426 | C47: 1 | D47: 1 | E47: 225 | F47: 0 | G47: 1571 | H47: 1155 | I47: 1155 | J47: -416 | K47: 416 | L47: -416 | M47: 10C001.076 | N47: CORALAN FC TAB 5 MG | O47: CORALAN FC TAB 5 MG | P47: OBAT PADAT (PERSEDIAAN LAINNYA)
A48: 1010401999 | B48: 001024 | C48: 1 | D48: 1 | E48: 4874 | F48: 0 | G48: 272 | K48: 272 | L48: -272 | M48: 10C001.10 | N48: CALCIUM POLYSTYRENE SULFONATE SERBUK 5G | O48: CALCIUM POLYSTYRENE SULFONATE SERBUK 5G | P48: OBAT LAINNYA (PERSEDIAAN LAINNYA)
A49: 1010401999 | B49: 001046 | C49: 2 | D49: 2 | E49: 14336 | F49: 0 | G49: 2951 | H49: 1141 | I49: 1141 | J49: -1810 | K49: 1810 | L49: -1810 | M49: 10C001.105 | N49: CETIRIZINE TAB 10 MG | O49: CETIRIZINE TAB 10 MG | P49: OBAT PADAT (PERSEDIAAN LAINNYA)
A50: 1010401002 | B50: 000421 | C50: 1 | D50: 1 | E50: 36592 | F50: 0 | G50: 5307 | H50: 1622 | I50: 1622 | J50: -2205 | K50: 3685 | L50: -3685 | M50: 10C001.107 | N50: CEFIXIME CAP 200 MG | O50: CEFIXIME CAP 200 MG | P50: OBAT PADAT (PERSEDIAAN LAINNYA)
A51: 1010401002 | B51: 000553 | C51: 1 | D51: 1 | E51: 0 | F51: 0 | G51: 70 | H51: 55 | I51: 55 | J51: -15 | K51: 15 | L51: -15 | M51: 10C001.118 | N51: CARDIO ASPIRIN TAB 100 MG | O51: CARDIO ASPIRIN TAB 100 MG | P51: OBAT PADAT (PERSEDIAAN LAINNYA)
A52: 1010401999 | B52: 003552 | C52: 1 | D52: 1 | E52: 1829 | F52: 0 | G52: 1921 | H52: 1643.12 | I52: 1644 | J52: -277.88 | K52: 277.88 | L52: -277.88 | M52: 10C001.13 | N52: CLOZAPINE TAB 100MG | O52: CLOZAPINE TAB 100MG | P52: OBAT LAINNYA (PERSEDIAAN LAINNYA)
A53: 1010401999 | B53: 003549 | C53: 1 | D53: 1 | E53: 13465 | F53: 0 | G53: 6485 | H53: 2487 | I53: 2487 | J53: -3998 | K53: 3998 | L53: -3998 | M53: 10C001.187 | N53: CONCOR TAB 1,25 MG | O53: CONCOR TAB 1,25 MG | P53: OBAT LAINNYA (PERSEDIAAN LAINNYA)
A54: 1010401999 | B54: 003548 | C54: 1 | D54: 1 | E54: 12 | F54: 0 | G54: 37 | K54: 37 | L54: -37 | M54: 10C001.1872 | N54: CURCUMA SANBE FCT 20 MG | O54: CURCUMA SANBE FCT 20 MG | P54: OBAT LAINNYA (PERSEDIAAN LAINNYA)
A55: 1010401999 | B55: 003547 | C55: 1 | D55: 1 | E55: 4578 | F55: 0 | G55: 4937 | H55: 2946 | I55: 2946 | J55: -1991 | K55: 1991 | L55: -1991 | M55: 10C001.188 | N55: CONCOR TAB 10 MG | O55: CONCOR TAB 10 MG | P55: OBAT LAINNYA (PERSEDIAAN LAINNYA)
A56: 1010401999 | B56: 000195 | C56: 1 | D56: 1 | E56: 0 | F56: 0 | G56: 30 | K56: 30 | L56: -30 | M56: 10C001.21 | N56: CALGAE KAPLET SALUT SELAPUT | O56: CALGAE KAPLET SALUT SELAPUT | P56: OBAT LAINNYA (PERSEDIAAN LAINNYA)
A57: 1010401999 | B57: 003546 | C57: 1 | D57: 1 | E57: 15361 | F57: 0 | G57: 248 | H57: 71 | I57: 71 | J57: -133 | K57: 177 | L57: -177 | M57: 10C001.23 | N57: CAPTOPRIL 50 MG TAB | O57: CAPTOPRIL 50 MG TAB | P57: OBAT LAINNYA (PERSEDIAAN LAINNYA)
A58: 1010401999 | B58: 003550 | C58: 2 | D58: 3 | E58: 4140 | F58: 0 | G58: 6490 | H58: 2695 | I58: 2695 | J58: -783 | K58: 3795 | L58: -3795 | M58: 10C001.25 | N58: CITICOLINE 500MG TABLET | O58: CITICOLINE TAB 500MG | P58: OBAT PADAT (PERSEDIAAN LAINNYA)
A59: 1010401002 | B59: 000545 | C59: 1 | D59: 1 | E59: 0 | F59: 0 | G59: 898 | H59: 360 | I59: 360 | J59: -538 | K59: 538 | L59: -538 | M59: 10C001.26 | N59: CLOFRITIS TAB 10MG | O59: CLOFRITIS TAB 10MG | P59: OBAT PADAT (PERSEDIAAN LAINNYA)
A60: 1010401002 | B60: 000558 | C60: 1 | D60: 1 | E60: 0 | F60: 0 | G60: 211 | H60: 160 | I60: 160 | J60: -51 | K60: 51 | L60: -51 | M60: 10C001.28 | N60: CETEME TAB | O60: CETEME TAB | P60: OBAT PADAT (PERSEDIAAN LAINNYA)
A61: 1010401999 | B61: 001071 | C61: 1 | D61: 1 | E61: 1033 | F61: 0 | G61: 29 | H61: 14 | I61: 14 | J61: -15 | K61: 15 | L61: -15 | M61: 10C001.3 | N61: CTM TAB 4MG | O61: CTM TAB 4MG | P61: OBAT LAINNYA (PERSEDIAAN LAINNYA)
A62: 1010401999 | B62: 001148 | C62: 1 | D62: 1 | E62: 35127 | F62: 0 | G62: 32236 | H62: 32181 | I62: 32181 | J62: -55 | K62: 55 | L62: -55 | M62: 10C001.7 | N62: COLCHICINE TABLET | O62: COLCHICINE TABLET | P62: OBAT LAINNYA (PERSEDIAAN LAINNYA)
A63: 1010401001 | B63: 000528 | C63: 1 | D63: 2 | E63: 0 | F63: 0 | G63: 1 | K63: 1 | L63: -1 | M63: 10C001.8 | N63: CEFIXIME SYR 100MG/5ML, 30ML | O63: CEFIXIME SYR 100MG/5ML, 30ML | P63: OBAT LAINNYA (PERSEDIAAN LAINNYA)
A64: 1010401002 | B64: 000111 | C64: 1 | D64: 1 | E64: 0 | F64: 0 | G64: 21 | K64: 21 | L64: -21 | M64: 10C001.9 | N64: CILOSTAZOL TAB 100 MG | O64: CILOSTAZOL TAB 100 MG | P64: OBAT PADAT (PERSEDIAAN LAINNYA)
A65: 1010401002 | B65: 000569 | C65: 1 | D65: 1 | E65: 0 | F65: 0 | G65: 120 | H65: 90 | I65: 90 | J65: -30 | K65: 30 | L65: -30 | M65: 10C01.27 | N65: CONCERTA TAB LEPAS LAMBAT 18MG | O65: CONCERTA TAB LEPAS LAMBAT 18MG | P65: OBAT PADAT (PERSEDIAAN LAINNYA)
A66: 1010401002 | B66: 000418 | C66: 2 | D66: 2 | E66: 13484 | F66: 0 | G66: 15146 | H66: 14476.2 | I66: 14477 | J66: -669.8 | K66: 669.8 | L66: -669.8 | M66: 10C018 | N66: CAPTOPRIL TAB 12.5 MG | O66: CAPTOPRIL TAB 12.5 MG | P66: OBAT PADAT (PERSEDIAAN LAINNYA)
A67: 1010401002 | B67: 000414 | C67: 1 | D67: 1 | E67: 56 | F67: 0 | G67: 41 | K67: 41 | L67: -41 | M67: 10C032.1 | N67: CAVIT D3 TAB | O67: CAVIT D3 TAB | P67: OBAT PADAT (PERSEDIAAN LAINNYA)
A68: 1010401002 | B68: 000411 | C68: 1 | D68: 1 | E68: 11368 | F68: 0 | G68: 5288 | H68: 4171 | I68: 4171 | J68: -1117 | K68: 1117 | L68: -1117 | M68: 10C100 | N68: CODEIN TAB 10 MG | O68: CODEIN TAB 10 MG | P68: OBAT PADAT (PERSEDIAAN LAINNYA)
A69: 1010401002 | B69: 000408 | C69: 1 | D69: 1 | E69: 173 | F69: 0 | G69: 262 | H69: 171 | I69: 171 | J69: -91 | K69: 91 | L69: -91 | M69: 10C104 | N69: CODIPRONT CUM EXP. CAPSUL | O69: CODIPRONT CUM EXP. CAPSUL | P69: OBAT PADAT (PERSEDIAAN LAINNYA)
A70: 1010401999 | B70: 000684 | C70: 2 | D70: 2 | E70: 3699 | F70: 0 | G70: 1 | K70: 1 | L70: -1 | M70: 10C149 | N70: CLOBAZAM TAB 10 MG | O70: CLOBAZAM TABLET 10MG | P70: OBAT PADAT (PERSEDIAAN LAINNYA)
A71: 1010401002 | B71: 000401 | C71: 1 | D71: 1 | E71: 1589 | F71: 0 | G71: 124 | H71: 87.5 | I71: 88 | J71: -36.5 | K71: 36.5 | L71: -36.5 | M71: 10D058 | N71: DIAZEPAM TABLET 5 MG | O71: DIAZEPAM TABLET 5 MG | P71: OBAT PADAT (PERSEDIAAN LAINNYA)
A72: 1010401002 | B72: 000386 | C72: 2 | D72: 2 | E72: 10094 | F72: 0 | G72: 9975 | H72: 8646 | I72: 8646 | J72: -1329 | K72: 1329 | L72: -1329 | M72: 10D071 | N72: DILTIAZEM TAB 30 MG | O72: DILTIAZEM TAB 30 MG | P72: OBAT PADAT (PERSEDIAAN LAINNYA)
A73: 1010401002 | B73: 000399 | C73: 1 | D73: 1 | E73: 439 | F73: 0 | G73: 955 | H73: 782.5 | I73: 783 | J73: -172.5 | K73: 172.5 | L73: -172.5 | M73: 10D074 | N73: DIMENHYDRINATE TABLET 50 MG | O73: DIMENHYDRINATE TABLET 50 MG | P73: OBAT PADAT (PERSEDIAAN LAINNYA)
A74: 1010401002 | B74: 000550 | C74: 1 | D74: 1 | E74: 0 | F74: 0 | G74: 2027 | H74: 1513 | I74: 1513 | J74: -514 | K74: 514 | L74: -514 | M74: 10D088 | N74: DIAGIT TABLET | O74: DIAGIT TABLET | P74: OBAT PADAT (PERSEDIAAN LAINNYA)
A75: 1010401002 | B75: 000398 | C75: 1 | D75: 1 | E75: 1935 | F75: 0 | G75: 1999 | H75: 1880 | I75: 1880 | J75: -119 | K75: 119 | L75: -119 | M75: 10D095 | N75: DOPAMET 250 mg | O75: DOPAMET 250 mg | P75: OBAT PADAT (PERSEDIAAN LAINNYA)
A76: 1010401002 | B76: 000396 | C76: 1 | D76: 1 | E76: 29 | F76: 0 | G76: 108 | H76: 68 | I76: 68 | J76: -40 | K76: 40 | L76: -40 | M76: 10D113 | N76: DUPHASTON TABLET 10 MG | O76: DUPHASTON TABLET 10 MG | P76: OBAT PADAT (PERSEDIAAN LAINNYA)
A77: 1010401002 | B77: 000395 | C77: 1 | D77: 1 | E77: 1895 | F77: 0 | G77: 70 | H77: 55 | I77: 55 | J77: -9 | K77: 15 | L77: -15 | M77: 10D148 | N77: DEPAKOTE. ER TAB 250 MG | O77: DEPAKOTE. ER TAB 250 MG | P77: OBAT PADAT (PERSEDIAAN LAINNYA)
A78: 1010401002 | B78: 000394 | C78: 1 | D78: 1 | E78: 3398 | F78: 0 | G78: 15 | K78: 15 | L78: -15 | M78: 10D149 | N78: DEPAKOTE. ER TAB 500 MG | O78: DEPAKOTE. ER TAB 500 MG | P78: OBAT PADAT (PERSEDIAAN LAINNYA)
A79: 1010401002 | B79: 000391 | C79: 1 | D79: 1 | E79: 490 | F79: 0 | G79: 190 | H79: 91 | I79: 91 | J79: -99 | K79: 99 | L79: -99 | M79: 10D168 | N79: DORNER TAB 20 MCG | O79: DORNER TAB 20 MCG | P79: OBAT PADAT (PERSEDIAAN LAINNYA)
A80: 1010401002 | B80: 000389 | C80: 1 | D80: 1 | E80: 168 | F80: 0 | G80: 393 | H80: 210.5 | I80: 211 | J80: -182.5 | K80: 182.5 | L80: -182.5 | M80: 10D175 | N80: DIGOXIN TAB 0.25 MG | O80: DIGOXIN TAB 0.25 MG | P80: OBAT PADAT (PERSEDIAAN LAINNYA)
A81: 1010401999 | B81: 003542 | C81: 1 | D81: 1 | E81: 259 | F81: 0 | G81: 137 | H81: 126 | I81: 126 | J81: -11 | K81: 11 | L81: -11 | M81: 10D192 | N81: DONEPEZIL HCL TAB 5MG | O81: DONEPEZIL HCL TAB 5MG | P81: OBAT LAINNYA (PERSEDIAAN LAINNYA)
A82: 1010401999 | B82: 003540 | C82: 1 | D82: 1 | E82: 1259 | F82: 0 | G82: 1561 | H82: 1208 | I82: 1208 | J82: -353 | K82: 353 | L82: -353 | M82: 10D197 | N82: DIOS TABLET 500 MG | O82: DIOS TABLET 500 MG | P82: OBAT LAINNYA (PERSEDIAAN LAINNYA)
A83: 1010401999 | B83: 000598 | C83: 1 | D83: 1 | E83: 1452 | F83: 0 | G83: 2531 | H83: 1870 | I83: 1870 | J83: -661 | K83: 661 | L83: -661 | M83: 10D203 | N83: DIVALPROEX SODIUM TABLET SALUT ENTERIK 250MG | O83: DIVALPROEX SODIUM TABLET SALUT ENTERIK 250MG | P83: OBAT LAINNYA (PERSEDIAAN LAINNYA)
A84: 1010401999 | B84: 003654 | C84: 1 | D84: 1 | E84: 0 | F84: 0 | G84: 1071 | H84: 586 | I84: 586 | J84: -485 | K84: 485 | L84: -485 | M84: 10D206 | N84: DUTASTERIDE KAPSUL 0.5MG | O84: DUTASTERIDE KAPSUL 0.5MG | P84: OBAT LAINNYA (PERSEDIAAN LAINNYA)
A85: 1010401002 | B85: 000100 | C85: 2 | D85: 3 | E85: 4298 | F85: 0 | G85: 22218 | H85: 181 | I85: 181 | J85: -385 | K85: 22037 | L85: -22037 | M85: 10D208 | N85: DEXAMETHASON TABLET 0,5 MG | O85: DEXAMETHASONE TAB 0,5MG | P85: OBAT PADAT (PERSEDIAAN LAINNYA)
A86: 1010401002 | B86: 000054 | C86: 2 | D86: 2 | E86: 1200 | F86: 0 | G86: 782 | H86: 440.5 | I86: 441 | J86: -341.5 | K86: 341.5 | L86: -341.5 | M86: 10E039 | N86: ERITROMISIN KAPSUL 500 MG | O86: ERYTROMICIN KAPL 500 MG | P86: OBAT PADAT (PERSEDIAAN LAINNYA)
A87: 1010401002 | B87: 000383 | C87: 1 | D87: 1 | E87: 647 | F87: 0 | G87: 163 | H87: 156 | I87: 156 | J87: -7 | K87: 7 | L87: -7 | M87: 10E070 | N87: EDOTIN KAPSUL 300 MG | O87: EDOTIN KAPSUL 300 MG | P87: OBAT PADAT (PERSEDIAAN LAINNYA)
A88: 1010401999 | B88: 003536 | C88: 1 | D88: 1 | E88: 31 | F88: 0 | G88: 22168 | H88: 16628.5 | I88: 16629 | J88: -5539.5 | K88: 5539.5 | L88: -5539.5 | M88: 10E096 | N88: ETHAMBUTOL TABLET 500MG | O88: ETHAMBUTOL TABLET 500MG | P88: OBAT LAINNYA (PERSEDIAAN LAINNYA)
A89: 1010401999 | B89: 003533 | C89: 1 | D89: 1 | E89: 4477 | F89: 0 | G89: 81 | K89: 81 | L89: -81 | M89: 10E099 | N89: EPERISON HCL 50 MG | O89: EPERISON HCL 50 MG | P89: OBAT LAINNYA (PERSEDIAAN LAINNYA)
A90: 1010401002 | B90: 000539 | C90: 1 | D90: 1 | E90: 0 | F90: 0 | G90: 250 | H90: 197 | I90: 197 | J90: -53 | K90: 53 | L90: -53 | M90: 10E104 | N90: ENTECAVIR TABLET 0.5MG | O90: ENTECAVIR TABLET 0.5MG | P90: OBAT PADAT (PERSEDIAAN LAINNYA)
A91: 1010401002 | B91: 000380 | C91: 1 | D91: 1 | E91: 48 | F91: 0 | G91: 17 | H91: 15 | I91: 15 | J91: -2 | K91: 2 | L91: -2 | M91: 10F015 | N91: FARNOMIN TABLET 50 MG | O91: FARNOMIN TABLET 50 MG | P91: OBAT PADAT (PERSEDIAAN LAINNYA)
A92: 1010401002 | B92: 000378 | C92: 1 | D92: 2 | E92: 315 | F92: 0 | G92: 66 | H92: 33 | I92: 33 | J92: 0 | K92: 33 | L92: -33 | M92: 10F043 | N92: FLUIMUCIL CAPSUL 200 mg | O92: FLUIMUCIL CAPSUL 200 mg | P92: OBAT PADAT (PERSEDIAAN LAINNYA)
A93: 1010401002 | B93: 000374 | C93: 1 | D93: 1 | E93: 338 | F93: 0 | G93: 556 | K93: 556 | L93: -556 | M93: 10F059 | N93: FUROSEMID TAB 40 MG | O93: FUROSEMID TAB 40 MG | P93: OBAT PADAT (PERSEDIAAN LAINNYA)
A94: 1010401002 | B94: 000373 | C94: 1 | D94: 1 | E94: 7351 | F94: 0 | G94: 1320 | H94: 1224 | I94: 1224 | J94: -96 | K94: 96 | L94: -96 | M94: 10F061 | N94: FARSORBID TAB 10 MG | O94: FARSORBID TAB 10 MG | P94: OBAT PADAT (PERSEDIAAN LAINNYA)
A95: 1010401002 | B95: 000549 | C95: 1 | D95: 1 | E95: 0 | F95: 0 | G95: 9271 | H95: 6917 | I95: 6917 | J95: -2354 | K95: 2354 | L95: -2354 | M95: 10F079 | N95: FARLOSIN TABLET SR 0,4 MG | O95: FARLOSIN TABLET SR 0,4 MG | P95: OBAT PADAT (PERSEDIAAN LAINNYA)
A96: 1010401002 | B96: 000595 | C96: 2 | D96: 2 | E96: 287 | F96: 0 | G96: 2774 | H96: 2669.5 | I96: 2670 | J96: -104.5 | K96: 104.5 | L96: -104.5 | M96: 10F099 | N96: FLUKONAZOL KAPSUL 150 MG | O96: FLUKONAZOL KAPSUL 150 MG | P96: OBAT PADAT (PERSEDIAAN LAINNYA)
A97: 1010401002 | B97: 000370 | C97: 1 | D97: 1 | E97: 720 | F97: 0 | G97: 1233 | H97: 1143 | I97: 1143 | J97: -90 | K97: 90 | L97: -90 | M97: 10F104 | N97: FENOKSIMETIL PENISILIN TABLET 250 MG | O97: FENOKSIMETIL PENISILIN TABLET 250 MG | P97: OBAT PADAT (PERSEDIAAN LAINNYA)
A98: 1010401002 | B98: 000369 | C98: 1 | D98: 1 | E98: 51 | F98: 0 | G98: 111 | H98: 109 | I98: 109 | J98: -2 | K98: 2 | L98: -2 | M98: 10F105 | N98: FENOKSIMETIL PENISILIN TABLET 500 MG | O98: FENOKSIMETIL PENISILIN TABLET 500 MG | P98: OBAT PADAT (PERSEDIAAN LAINNYA)
A99: 1010401002 | B99: 000511 | C99: 1 | D99: 1 | E99: 0 | F99: 0 | G99: 16 | K99: 16 | L99: -16 | M99: 10F116 | N99: FORRES TAB 50 MG | O99: FORRES TAB 50 MG | P99: OBAT PADAT (PERSEDIAAN LAINNYA)
A100: 1010401002 | B100: 000366 | C100: 1 | D100: 1 | E100: 8859 | F100: 0 | G100: 1361 | H100: 558 | I100: 558 | J100: -803 | K100: 803 | L100: -803 | M100: 10F144 | N100: FLUNARIZINE 5 MG TAB | O100: FLUNARIZINE 5 MG TAB | P100: OBAT PADAT (PERSEDIAAN LAINNYA)
...

Sheet selisihNol
A1: sakti_kode_klp | B1: sakti_kode | C1: katalog_grp | D1: sakti_grp | E1: qty_awal | F1: sakti_awal_add | G1: sakti_akhir | H1: simrs_akhir | I1: pembulatan | J1: simrs_trx | K1: selisih_abs | L1: selisih | M1: katalog_kode | N1: katalog_nama | O1: sakti_nama | P1: sakti_nama_klp
A2: 1010401999 | B2: 004174 | C2: 14 | D2: 14 | E2: 0 | F2: 0 | G2: 0 | K2: 0 | L2: 0 | O2: TAPROS 1.88 MG | P2: OBAT LAINNYA (PERSEDIAAN LAINNYA)
A3: 1010401002 | B3: 000477 | C3: 1 | D3: 1 | E3: 259 | F3: 0 | G3: 7 | H3: 7 | I3: 7 | J3: 0 | K3: 0 | L3: 0 | M3: 10A044 | N3: ALLORIS TABLET 10 MG | O3: ALLORIS TABLET 10 MG | P3: OBAT PADAT (PERSEDIAAN LAINNYA)
A4: 1010401002 | B4: 000473 | C4: 1 | D4: 1 | E4: 81 | F4: 0 | G4: 0 | K4: 0 | L4: 0 | M4: 10A085 | N4: ARCALION 200 TAB | O4: ARCALION 200 TAB | P4: OBAT PADAT (PERSEDIAAN LAINNYA)
A5: 1010401002 | B5: 000472 | C5: 1 | D5: 1 | E5: 30983 | F5: 0 | G5: 0 | K5: 0 | L5: 0 | M5: 10A095 | N5: ASAM FOLAT 1 MG | O5: ASAM FOLAT 1 MG | P5: OBAT PADAT (PERSEDIAAN LAINNYA)
A6: 1010401002 | B6: 000055 | C6: 1 | D6: 1 | E6: 265 | F6: 0 | G6: 0 | K6: 0 | L6: 0 | M6: 10A098 | N6: ASCARDIA TABLET SALUT ENTERIK 80 MG | O6: ASCARDIA TABLET SALUT ENTERIK 80 MG | P6: OBAT PADAT (PERSEDIAAN LAINNYA)
A7: 1010401002 | B7: 000471 | C7: 1 | D7: 1 | E7: 295 | F7: 0 | G7: 0 | K7: 0 | L7: 0 | M7: 10A112 | N7: ATIVAN TAB 1 MG | O7: ATIVAN TAB 1 MG | P7: OBAT PADAT (PERSEDIAAN LAINNYA)
A8: 1010401002 | B8: 000468 | C8: 1 | D8: 1 | E8: 326 | F8: 0 | G8: 20 | H8: 20 | I8: 20 | J8: 0 | K8: 0 | L8: 0 | M8: 10A164 | N8: ARCOXIA TAB 60 MG | O8: ARCOXIA TAB 60 MG | P8: OBAT PADAT (PERSEDIAAN LAINNYA)
A9: 1010401002 | B9: 000465 | C9: 1 | D9: 1 | E9: 20 | F9: 0 | G9: 0 | K9: 0 | L9: 0 | M9: 10A171 | N9: ABBOTIC XL TAB 500 MG | O9: ABBOTIC XL TAB 500 MG | P9: OBAT PADAT (PERSEDIAAN LAINNYA)
A10: 1010401002 | B10: 000023 | C10: 1 | D10: 1 | E10: 244 | F10: 0 | G10: 0 | K10: 0 | L10: 0 | M10: 10A175 | N10: ABILIFY 10 MG TAB | O10: ABILIFY 10 MG TAB | P10: OBAT PADAT (PERSEDIAAN LAINNYA)
A11: 1010401002 | B11: 000518 | C11: 1 | D11: 1 | E11: 0 | F11: 0 | G11: 0 | K11: 0 | L11: 0 | M11: 10A176 | N11: ABILIFY 15 MG TAB | O11: ABILIFY 15 MG TAB | P11: OBAT PADAT (PERSEDIAAN LAINNYA)
A12: 1010401002 | B12: 000464 | C12: 1 | D12: 1 | E12: 7222 | F12: 0 | G12: 19 | H12: 19 | I12: 19 | J12: 0 | K12: 0 | L12: 0 | M12: 10A177 | N12: AVODART TAB 0.5 MG | O12: AVODART TAB 0.5 MG | P12: OBAT PADAT (PERSEDIAAN LAINNYA)
A13: 1010401002 | B13: 000463 | C13: 1 | D13: 1 | E13: 75 | F13: 0 | G13: 40 | H13: 40 | I13: 40 | J13: 0 | K13: 0 | L13: 0 | M13: 10A185 | N13: ARTRODAR CAP 50 MG | O13: ARTRODAR CAP 50 MG | P13: OBAT PADAT (PERSEDIAAN LAINNYA)
A14: 1010401002 | B14: 000461 | C14: 1 | D14: 1 | E14: 23 | F14: 0 | G14: 0 | H14: 0 | I14: 0 | J14: 0 | K14: 0 | L14: 0 | M14: 10A200 | N14: AERIUS TAB 5 MG | O14: AERIUS TAB 5 MG | P14: OBAT PADAT (PERSEDIAAN LAINNYA)
A15: 1010401002 | B15: 000571 | C15: 1 | D15: 1 | E15: 0 | F15: 0 | G15: 300 | H15: 300 | I15: 300 | J15: 0 | K15: 0 | L15: 0 | M15: 10A201 | N15: ARIPIPRAZOLE TAB DISPERSIBEL 10MG | O15: ARIPIPRAZOLE TAB DISPERSIBEL 10MG | P15: OBAT PADAT (PERSEDIAAN LAINNYA)
A16: 1010401002 | B16: 000456 | C16: 1 | D16: 1 | E16: 1702 | F16: 0 | G16: 0 | K16: 0 | L16: 0 | M16: 10A255 | N16: ALPENTIN 100 MG CAPS | O16: ALPENTIN 100 MG CAPS | P16: OBAT PADAT (PERSEDIAAN LAINNYA)
A17: 1010401002 | B17: 000538 | C17: 1 | D17: 1 | E17: 0 | F17: 0 | G17: 0 | K17: 0 | L17: 0 | M17: 10A279 | N17: AMOXYCILLIN TAB 500 MG | O17: AMOXYCILLIN TAB 500 MG | P17: OBAT PADAT (PERSEDIAAN LAINNYA)
A18: 1010401002 | B18: 000447 | C18: 1 | D18: 1 | E18: 6 | F18: 0 | G18: 0 | K18: 0 | L18: 0 | M18: 10A281 | N18: ACYCLOVIR 200 MG TAB | O18: ACYCLOVIR 200 MG TAB | P18: OBAT PADAT (PERSEDIAAN LAINNYA)
A19: 1010401999 | B19: 003563 | C19: 1 | D19: 1 | E19: 334 | F19: 0 | G19: 0 | K19: 0 | L19: 0 | M19: 10A304 | N19: AVIGAN TAB 200 MG | O19: AVIGAN TAB 200 MG | P19: OBAT LAINNYA (PERSEDIAAN LAINNYA)
A20: 1010401002 | B20: 000527 | C20: 1 | D20: 1 | E20: 0 | F20: 0 | G20: 0 | K20: 0 | L20: 0 | M20: 10A317 | N20: ABILIFY TAB 5 MG | O20: ABILIFY TAB 5 MG | P20: OBAT PADAT (PERSEDIAAN LAINNYA)
A21: 1010401999 | B21: 000353 | C21: 1 | D21: 1 | E21: 294 | F21: 0 | G21: 294 | H21: 294 | I21: 294 | J21: 0 | K21: 0 | L21: 0 | M21: 10B058 | N21: BIOSAN TAB 275 MG | O21: BIOSAN TAB 275 MG | P21: OBAT LAINNYA (PERSEDIAAN LAINNYA)
A22: 1010401002 | B22: 000440 | C22: 1 | D22: 1 | E22: 188 | F22: 0 | G22: 0 | K22: 0 | L22: 0 | M22: 10B079 | N22: BUSCOPAN PLUS TAB | O22: BUSCOPAN PLUS TAB | P22: OBAT PADAT (PERSEDIAAN LAINNYA)
A23: 1010401002 | B23: 000439 | C23: 1 | D23: 1 | E23: 78 | F23: 0 | G23: 0 | K23: 0 | L23: 0 | M23: 10B093 | N23: BETASERC TAB 24 MG | O23: BETASERC TAB 24 MG | P23: OBAT PADAT (PERSEDIAAN LAINNYA)
A24: 1010401002 | B24: 000438 | C24: 1 | D24: 1 | E24: 0 | F24: 0 | G24: 12 | H24: 12 | I24: 12 | J24: 0 | K24: 0 | L24: 0 | M24: 10B117 | N24: BAQUINOR FORTE KAPL 500 MG | O24: BAQUINOR FORTE KAPL 500 MG | P24: OBAT PADAT (PERSEDIAAN LAINNYA)
A25: 1010401002 | B25: 000573 | C25: 1 | D25: 1 | E25: 0 | F25: 0 | G25: 9 | H25: 9 | I25: 9 | J25: 0 | K25: 0 | L25: 0 | M25: 10B143 | N25: BETARHIN 10MG TAB | O25: BETARHIN 10MG TAB | P25: OBAT PADAT (PERSEDIAAN LAINNYA)
A26: 1010401002 | B26: 000433 | C26: 1 | D26: 1 | E26: 27 | F26: 0 | G26: 4 | H26: 4 | I26: 4 | J26: 0 | K26: 0 | L26: 0 | M26: 10C001.026 | N26: CEFSPAN 200 MG | O26: CEFSPAN 200 MG | P26: OBAT PADAT (PERSEDIAAN LAINNYA)
A27: 1010401002 | B27: 000432 | C27: 1 | D27: 1 | E27: 9 | F27: 0 | G27: 3 | H27: 3 | I27: 3 | J27: 0 | K27: 0 | L27: 0 | M27: 10C001.027 | N27: CEFAT KAPSUL 500 MG | O27: CEFAT KAPSUL 500 MG | P27: OBAT PADAT (PERSEDIAAN LAINNYA)
A28: 1010401002 | B28: 000491 | C28: 1 | D28: 1 | E28: 0 | F28: 0 | G28: 0 | K28: 0 | L28: 0 | M28: 10C001.030 | N28: CELEBREX CAP 200 MG | O28: CELEBREX CAP 200 MG | P28: OBAT PADAT (PERSEDIAAN LAINNYA)
A29: 1010401002 | B29: 000085 | C29: 1 | D29: 1 | E29: 178 | F29: 0 | G29: 64 | H29: 64 | I29: 64 | J29: 0 | K29: 0 | L29: 0 | M29: 10C001.054 | N29: CIPRALEX TAB | O29: CIPRALEX TAB | P29: OBAT PADAT (PERSEDIAAN LAINNYA)
A30: 1010401002 | B30: 000121 | C30: 1 | D30: 1 | E30: 292 | F30: 0 | G30: 293 | H30: 293 | I30: 293 | J30: 0 | K30: 0 | L30: 0 | M30: 10C001.071 | N30: CODITAM TABLET | O30: CODITAM TABLET | P30: OBAT PADAT (PERSEDIAAN LAINNYA)
A31: 1010401002 | B31: 000510 | C31: 1 | D31: 1 | E31: 0 | F31: 0 | G31: 0 | K31: 0 | L31: 0 | M31: 10C001.1.14306 | N31: CYGEST TABLET 200 MG | O31: CYGEST TABLET 200 MG | P31: OBAT PADAT (PERSEDIAAN LAINNYA)
A32: 1010401999 | B32: 001595 | C32: 1 | D32: 1 | E32: 100 | F32: 0 | G32: 0 | K32: 0 | L32: 0 | M32: 10C001.11 | N32: CHLORAMEX TAB 500MG | O32: CHLORAMEX TAB 500MG | P32: OBAT LAINNYA (PERSEDIAAN LAINNYA)
A33: 1010401999 | B33: 001673 | C33: 1 | D33: 1 | E33: 1067 | F33: 0 | G33: 0 | K33: 0 | L33: 0 | M33: 10C001.6 | N33: CURCUMA FORCE TAB | O33: CURCUMA FORCE TAB | P33: OBAT LAINNYA (PERSEDIAAN LAINNYA)
A34: 1010401999 | B34: 003544 | C34: 1 | D34: 1 | E34: 661 | F34: 0 | G34: 0 | K34: 0 | L34: 0 | M34: 10C002 | N34: CERINI KAPL 10 MG | O34: CERINI KAPL 10 MG | P34: OBAT LAINNYA (PERSEDIAAN LAINNYA)
A35: 1010401999 | B35: 001205 | C35: 1 | D35: 1 | E35: 41 | F35: 0 | G35: 21 | H35: 21 | I35: 21 | J35: 0 | K35: 0 | L35: 0 | M35: 10C004 | N35: CALCIUM D REDOXON | O35: CALCIUM D REDOXON | P35: OBAT LAINNYA (PERSEDIAAN LAINNYA)
A36: 1010401002 | B36: 000417 | C36: 1 | D36: 1 | E36: 9327 | F36: 0 | G36: 202 | H36: 202 | I36: 202 | J36: 0 | K36: 0 | L36: 0 | M36: 10C019 | N36: CARBAMAZEPINE TAB 200 MG | O36: CARBAMAZEPINE TAB 200 MG | P36: OBAT PADAT (PERSEDIAAN LAINNYA)
A37: 1010401002 | B37: 000416 | C37: 1 | D37: 1 | E37: 63 | F37: 0 | G37: 0 | K37: 0 | L37: 0 | M37: 10C029 | N37: CATAFLAM TAB 25 MG | O37: CATAFLAM TAB 25 MG | P37: OBAT PADAT (PERSEDIAAN LAINNYA)
A38: 1010401002 | B38: 000415 | C38: 1 | D38: 1 | E38: 3 | F38: 0 | G38: 0 | K38: 0 | L38: 0 | M38: 10C029.1 | N38: CATAFLAM TAB 50 MG | O38: CATAFLAM TAB 50 MG | P38: OBAT PADAT (PERSEDIAAN LAINNYA)
A39: 1010401002 | B39: 000413 | C39: 1 | D39: 1 | E39: 10 | F39: 0 | G39: 0 | K39: 0 | L39: 0 | M39: 10C046 | N39: CEFSPAN CAPSUL 100 mg | O39: CEFSPAN CAPSUL 100 mg | P39: OBAT PADAT (PERSEDIAAN LAINNYA)
A40: 1010401002 | B40: 000566 | C40: 2 | D40: 2 | E40: 20555 | F40: 0 | G40: 0 | K40: 0 | L40: 0 | M40: 10C094 | N40: CLONIDIN TAB | O40: CLONIDINE TAB 0.15MG | P40: OBAT PADAT (PERSEDIAAN LAINNYA)
A41: 1010401002 | B41: 000544 | C41: 1 | D41: 1 | E41: 0 | F41: 0 | G41: 180 | H41: 180 | I41: 180 | J41: 0 | K41: 0 | L41: 0 | M41: 10C098 | N41: COBAZIM 1000 MCG | O41: COBAZIM 1000 MCG | P41: OBAT PADAT (PERSEDIAAN LAINNYA)
A42: 1010401002 | B42: 000409 | C42: 1 | D42: 1 | E42: 232 | F42: 0 | G42: 592 | H42: 592 | I42: 592 | J42: 0 | K42: 0 | L42: 0 | M42: 10C103 | N42: CODIPRONT CAPSUL | O42: CODIPRONT CAPSUL | P42: OBAT PADAT (PERSEDIAAN LAINNYA)
A43: 1010401002 | B43: 000507 | C43: 1 | D43: 1 | E43: 0 | F43: 0 | G43: 0 | K43: 0 | L43: 0 | M43: 10C126 | N43: CURVIT TAB | O43: CURVIT TAB | P43: OBAT PADAT (PERSEDIAAN LAINNYA)
A44: 1010401002 | B44: 000404 | C44: 1 | D44: 1 | E44: 144 | F44: 0 | G44: 100 | H44: 100 | I44: 100 | J44: 0 | K44: 0 | L44: 0 | M44: 10D004 | N44: DALFAROL KAP LUNAK 200 IU | O44: DALFAROL KAP LUNAK 200 IU | P44: OBAT PADAT (PERSEDIAAN LAINNYA)
A45: 1010401002 | B45: 000403 | C45: 1 | D45: 1 | E45: 165 | F45: 0 | G45: 0 | K45: 0 | L45: 0 | M45: 10D031 | N45: DEPAKOTE TABLET 250 MG | O45: DEPAKOTE TABLET 250 MG | P45: OBAT PADAT (PERSEDIAAN LAINNYA)
A46: 1010401002 | B46: 000402 | C46: 1 | D46: 1 | E46: 326 | F46: 0 | G46: 0 | K46: 0 | L46: 0 | M46: 10D043 | N46: DEXTAMINE TABLET 0,5 MG | O46: DEXTAMINE TABLET 0,5 MG | P46: OBAT PADAT (PERSEDIAAN LAINNYA)
A47: 1010401002 | B47: 000505 | C47: 1 | D47: 1 | E47: 0 | F47: 0 | G47: 0 | K47: 0 | L47: 0 | M47: 10D089 | N47: DOLO NEUROBION TABLET | O47: DOLO NEUROBION TABLET | P47: OBAT PADAT (PERSEDIAAN LAINNYA)
A48: 1010401002 | B48: 000397 | C48: 1 | D48: 1 | E48: 26 | F48: 0 | G48: 0 | K48: 0 | L48: 0 | M48: 10D101 | N48: DOXYCYCLINE CAP 100 MG | O48: DOXYCYCLINE CAP 100 MG | P48: OBAT PADAT (PERSEDIAAN LAINNYA)
A49: 1010401002 | B49: 000089 | C49: 1 | D49: 1 | E49: 46 | F49: 0 | G49: 0 | K49: 0 | L49: 0 | M49: 10D105 | N49: DULCOLAX TABLET 5 mg | O49: DULCOLAX TABLET 5 mg | P49: OBAT PADAT (PERSEDIAAN LAINNYA)
A50: 1010401002 | B50: 000494 | C50: 1 | D50: 1 | E50: 0 | F50: 0 | G50: 4 | H50: 4 | I50: 4 | J50: 0 | K50: 0 | L50: 0 | M50: 10D140 | N50: DOXICOR KAPSUL 100 MG | O50: DOXICOR KAPSUL 100 MG | P50: OBAT PADAT (PERSEDIAAN LAINNYA)
A51: 1010401002 | B51: 000393 | C51: 1 | D51: 1 | E51: 1 | F51: 0 | G51: 0 | K51: 0 | L51: 0 | M51: 10D158.14204 | N51: DIAMICRON MR TABLET 60 MG | O51: DIAMICRON MR TABLET SR 60 MG | P51: OBAT PADAT (PERSEDIAAN LAINNYA)
A52: 1010401999 | B52: 003538 | C52: 1 | D52: 1 | E52: 300 | F52: 0 | G52: 0 | K52: 0 | L52: 0 | M52: 10D199 | N52: DIAFAC XR | O52: DIAFAC XR | P52: OBAT LAINNYA (PERSEDIAAN LAINNYA)
A53: 1010401999 | B53: 003333 | C53: 2 | D53: 2 | E53: 126 | F53: 0 | G53: 2 | H53: 2 | I53: 2 | J53: -1 | K53: 0 | L53: 0 | M53: 10D199.1 | N53: DOMPERIDONE SUSP 60ML | O53: DOMPERIDONE SUSP 60ML | P53: OBAT LAINNYA (PERSEDIAAN LAINNYA)
A54: 1010401999 | B54: 001163 | C54: 1 | D54: 1 | E54: 133 | F54: 0 | G54: 0 | K54: 0 | L54: 0 | M54: 10D201 | N54: DOXYCYCLINE KAPSUL 100MG | O54: DOXYCYCLINE KAPSUL 100MG | P54: OBAT LAINNYA (PERSEDIAAN LAINNYA)
A55: 1010401002 | B55: 000519 | C55: 1 | D55: 1 | E55: 0 | F55: 0 | G55: 0 | K55: 0 | L55: 0 | M55: 10D210 | N55: DELOSDIN 5 MG TAB | O55: DELOSDIN 5 MG TAB | P55: OBAT PADAT (PERSEDIAAN LAINNYA)
A56: 1010401999 | B56: 003537 | C56: 1 | D56: 1 | E56: 18 | F56: 0 | G56: 0 | K56: 0 | L56: 0 | M56: 10E004 | N56: EFLAGEN 50MG TABLET | O56: EFLAGEN 50MG TABLET | P56: OBAT LAINNYA (PERSEDIAAN LAINNYA)
A57: 1010401002 | B57: 000040 | C57: 1 | D57: 1 | E57: 2 | F57: 0 | G57: 47 | H57: 47 | I57: 47 | J57: 0 | K57: 0 | L57: 0 | M57: 10E031 | N57: ERICAF TABLET 1 MG | O57: ERICAF TABLET 1 MG | P57: OBAT PADAT (PERSEDIAAN LAINNYA)
A58: 1010401002 | B58: 000385 | C58: 1 | D58: 1 | E58: 9 | F58: 0 | G58: 0 | K58: 0 | L58: 0 | M58: 10E033.14197 | N58: ERYSANBE KAPSUL 500 MG | O58: ERYSANBE KAPSUL 500 MG | P58: OBAT PADAT (PERSEDIAAN LAINNYA)
A59: 1010401002 | B59: 000381 | C59: 1 | D59: 1 | E59: 0 | F59: 0 | G59: 7 | H59: 7 | I59: 7 | J59: 0 | K59: 0 | L59: 0 | M59: 10E086 | N59: EUTHYROX TAB 100 MCG | O59: EUTHYROX TAB 100 MCG | P59: OBAT PADAT (PERSEDIAAN LAINNYA)
A60: 1010401002 | B60: 000543 | C60: 1 | D60: 1 | E60: 0 | F60: 0 | G60: 90 | H60: 90 | I60: 90 | J60: 0 | K60: 0 | L60: 0 | M60: 10E100 | N60: EZETROL TAB | O60: EZETROL TAB | P60: OBAT PADAT (PERSEDIAAN LAINNYA)
A61: 1010401999 | B61: 003532 | C61: 1 | D61: 1 | E61: 175 | F61: 0 | G61: 0 | K61: 0 | L61: 0 | M61: 10F035 | N61: FLAMAR TAB 50 MG | O61: FLAMAR TAB 50 MG | P61: OBAT LAINNYA (PERSEDIAAN LAINNYA)
A62: 1010401002 | B62: 000377 | C62: 1 | D62: 1 | E62: 30 | F62: 0 | G62: 0 | K62: 0 | L62: 0 | M62: 10F044 | N62: FLUIMUCIL EFFERVESC 600 mg | O62: FLUIMUCIL EFFERVESC 600 mg | P62: OBAT PADAT (PERSEDIAAN LAINNYA)
A63: 1010401002 | B63: 000376 | C63: 1 | D63: 1 | E63: 72 | F63: 0 | G63: 363 | H63: 363 | I63: 363 | J63: 0 | K63: 0 | L63: 0 | M63: 10F046 | N63: FLUIMUCIL GRANULE 200 mg | O63: FLUIMUCIL GRANULE 200 mg | P63: OBAT PADAT (PERSEDIAAN LAINNYA)
A64: 1010401002 | B64: 000375 | C64: 1 | D64: 1 | E64: 188 | F64: 0 | G64: 136 | H64: 136 | I64: 136 | J64: 0 | K64: 0 | L64: 0 | M64: 10F052 | N64: FORMALIN 1 g | O64: FORMALIN 1 g | P64: OBAT PADAT (PERSEDIAAN LAINNYA)
A65: 1010401002 | B65: 000372 | C65: 1 | D65: 1 | E65: 180 | F65: 0 | G65: 0 | K65: 0 | L65: 0 | M65: 10F093 | N65: FOLAMIL GENIO CAP LUNAK | O65: FOLAMIL GENIO CAP LUNAK | P65: OBAT PADAT (PERSEDIAAN LAINNYA)
A66: 1010401002 | B66: 000489 | C66: 1 | D66: 1 | E66: 0 | F66: 0 | G66: 0 | K66: 0 | L66: 0 | M66: 10F096 | N66: FITBON KAPL 500 MG | O66: FITBON KAPL 500 MG | P66: OBAT PADAT (PERSEDIAAN LAINNYA)
A67: 1010401002 | B67: 000368 | C67: 1 | D67: 1 | E67: 409 | F67: 0 | G67: 0 | K67: 0 | L67: 0 | M67: 10F117 | N67: FREGO TAB 5 MG | O67: FREGO TAB 5 MG | P67: OBAT PADAT (PERSEDIAAN LAINNYA)
A68: 1010401002 | B68: 000367 | C68: 1 | D68: 1 | E68: 365 | F68: 0 | G68: 29 | H68: 29 | I68: 29 | J68: 0 | K68: 0 | L68: 0 | M68: 10F120 | N68: FORNEURO CAP LUNAK | O68: FORNEURO CAP LUNAK | P68: OBAT PADAT (PERSEDIAAN LAINNYA)
A69: 1010401999 | B69: 001430 | C69: 1 | D69: 1 | E69: 169 | F69: 0 | G69: 0 | K69: 0 | L69: 0 | M69: 10F152 | N69: FLUCONAZOLE 150 MG | O69: FLUCONAZOLE 150 MG | P69: OBAT LAINNYA (PERSEDIAAN LAINNYA)
A70: 1010401002 | B70: 000555 | C70: 1 | D70: 1 | E70: 0 | F70: 0 | G70: 0 | K70: 0 | L70: 0 | M70: 10F153.1 | N70: FEBURIC 80MG TAB | O70: FEBURIC 80MG TAB | P70: OBAT PADAT (PERSEDIAAN LAINNYA)
A71: 1010401999 | B71: 001154 | C71: 1 | D71: 1 | E71: 7790 | F71: 0 | G71: 0 | K71: 0 | L71: 0 | M71: 10F157 | N71: FLUVIR TABLET 75MG | O71: FLUVIR TABLET 75MG | P71: OBAT LAINNYA (PERSEDIAAN LAINNYA)
A72: 1010401999 | B72: 000727 | C72: 1 | D72: 1 | E72: 10000 | F72: 0 | G72: 0 | K72: 0 | L72: 0 | M72: 10F158 | N72: FAVIKAL TAB 200MG | O72: FAVIKAL TAB 200MG | P72: OBAT LAINNYA (PERSEDIAAN LAINNYA)
A73: 1010401002 | B73: 000526 | C73: 1 | D73: 1 | E73: 0 | F73: 0 | G73: 0 | K73: 0 | L73: 0 | M73: 10F164 | N73: FARMADOL 500 MG TAB | O73: FARMADOL 500 MG TAB | P73: OBAT PADAT (PERSEDIAAN LAINNYA)
A74: 1010401002 | B74: 000529 | C74: 1 | D74: 1 | E74: 0 | F74: 0 | G74: 30 | H74: 30 | I74: 30 | J74: 0 | K74: 0 | L74: 0 | M74: 10G035 | N74: GRISEOFULVIN TABLET 125 MG | O74: GRISEOFULVIN TABLET 125 MG | P74: OBAT PADAT (PERSEDIAAN LAINNYA)
A75: 1010401002 | B75: 000360 | C75: 1 | D75: 1 | E75: 1965 | F75: 0 | G75: 0 | K75: 0 | L75: 0 | M75: 10G096 | N75: GLISERIL GUAYAKOLAT TABLET 100 MG | O75: GLISERIL GUAYAKOLAT TABLET 100 MG | P75: OBAT PADAT (PERSEDIAAN LAINNYA)
A76: 1010401002 | B76: 000358 | C76: 1 | D76: 1 | E76: 306 | F76: 0 | G76: 8 | H76: 8 | I76: 8 | J76: 0 | K76: 0 | L76: 0 | M76: 10G104 | N76: GLUCOSAMINE 250 MG KAP | O76: GLUCOSAMINE 250 MG KAP | P76: OBAT PADAT (PERSEDIAAN LAINNYA)
A77: 1010401999 | B77: 000184 | C77: 1 | D77: 1 | E77: 100 | F77: 0 | G77: 151 | H77: 151 | I77: 151 | J77: 0 | K77: 0 | L77: 0 | M77: 10G133 | N77: GLICLAZIDE 80MG TAB | O77: GLICLAZIDE 80MG TAB | P77: OBAT LAINNYA (PERSEDIAAN LAINNYA)
A78: 1010401002 | B78: 000508 | C78: 1 | D78: 1 | E78: 0 | F78: 0 | G78: 0 | K78: 0 | L78: 0 | M78: 10G136 | N78: GLUCOPHAGE XR 1000MG | O78: GLUCOPHAGE XR 1000MG | P78: OBAT PADAT (PERSEDIAAN LAINNYA)
A79: 1010401002 | B79: 000561 | C79: 1 | D79: 1 | E79: 0 | F79: 0 | G79: 0 | K79: 0 | L79: 0 | M79: 10H047 | N79: HYPOFIL KAPSUL 300 MG | O79: HAEMOGAL CAPLET | P79: OBAT PADAT (PERSEDIAAN LAINNYA)
A80: 1010401002 | B80: 000352 | C80: 1 | D80: 1 | E80: 0 | F80: 0 | G80: 11 | H80: 11 | I80: 11 | J80: 0 | K80: 0 | L80: 0 | M80: 10H055 | N80: HEPA-MERZ GRANUL SACHET 3 G | O80: HEPA-MERZ GRANUL SACHET 3 G | P80: OBAT PADAT (PERSEDIAAN LAINNYA)
A81: 1010401002 | B81: 000524 | C81: 1 | D81: 1 | E81: 0 | F81: 0 | G81: 0 | K81: 0 | L81: 0 | M81: 10H074 | N81: HEXYMER TAB 2 MG | O81: HEXYMER TAB 2 MG | P81: OBAT PADAT (PERSEDIAAN LAINNYA)
A82: 1010401999 | B82: 003521 | C82: 1 | D82: 1 | E82: 60 | F82: 0 | G82: 0 | K82: 0 | L82: 0 | M82: 10H100 | N82: HEZANDRA KAPLET | O82: HEZANDRA KAPLET | P82: OBAT LAINNYA (PERSEDIAAN LAINNYA)
A83: 1010401002 | B83: 000584 | C83: 1 | D83: 1 | E83: 0 | F83: 0 | G83: 45 | H83: 45 | I83: 45 | J83: 0 | K83: 0 | L83: 0 | M83: 10H105 | N83: HERBAPAIN TABLET | O83: HERBAPAIN TABLET | P83: OBAT PADAT (PERSEDIAAN LAINNYA)
A84: 1010401002 | B84: 000482 | C84: 1 | D84: 1 | E84: 0 | F84: 0 | G84: 0 | K84: 0 | L84: 0 | M84: 10I741 | N84: ITRACONAZOLE 100 MG CAP | O84: ITRACONAZOLE 100 MG CAP | P84: OBAT PADAT (PERSEDIAAN LAINNYA)
A85: 1010401002 | B85: 000564 | C85: 1 | D85: 1 | E85: 0 | F85: 0 | G85: 10 | H85: 10 | I85: 10 | J85: 0 | K85: 0 | L85: 0 | M85: 10I744 | N85: IRBESARTAN TABLET 150 MG | O85: IRBESARTAN TABLET 150 MG | P85: OBAT PADAT (PERSEDIAAN LAINNYA)
A86: 1010401999 | B86: 003518 | C86: 1 | D86: 1 | E86: 35 | F86: 0 | G86: 0 | K86: 0 | L86: 0 | M86: 10I756 | N86: INVITEC TAB 200 MCG | O86: INVITEC TAB 200 MCG | P86: OBAT LAINNYA (PERSEDIAAN LAINNYA)
A87: 1010401999 | B87: 003517 | C87: 1 | D87: 1 | E87: 0 | F87: 0 | G87: 0 | K87: 0 | L87: 0 | M87: 10I757 | N87: INBUMIN TAB 250MG | O87: INBUMIN TAB 250MG | P87: OBAT LAINNYA (PERSEDIAAN LAINNYA)
A88: 1010401999 | B88: 000194 | C88: 1 | D88: 1 | E88: 260 | F88: 0 | G88: 0 | K88: 0 | L88: 0 | M88: 10I757.1 | N88: ISIVAS TAB 10MG | O88: ISIVAS TAB 10MG | P88: OBAT LAINNYA (PERSEDIAAN LAINNYA)
A89: 1010401999 | B89: 001086 | C89: 1 | D89: 1 | E89: 164 | F89: 0 | G89: 0 | K89: 0 | L89: 0 | M89: 10I758 | N89: IBUPROFEN 200MG TAB | O89: IBUPROFEN 200MG TAB | P89: OBAT LAINNYA (PERSEDIAAN LAINNYA)
A90: 1010401999 | B90: 000726 | C90: 1 | D90: 1 | E90: 4705 | F90: 0 | G90: 0 | K90: 0 | L90: 0 | M90: 10I760 | N90: IVERMECTIN TAB 12MG | O90: IVERMECTIN TAB 12MG | P90: OBAT LAINNYA (PERSEDIAAN LAINNYA)
A91: 1010401002 | B91: 000002 | C91: 1 | D91: 1 | E91: 3 | F91: 0 | G91: 0 | K91: 0 | L91: 0 | M91: 10K024 | N91: KETOSTERIL TAB 630 MG | O91: KETOSTERIL TAB 630 MG | P91: OBAT PADAT (PERSEDIAAN LAINNYA)
A92: 1010401002 | B92: 000332 | C92: 1 | D92: 1 | E92: 131 | F92: 0 | G92: 0 | K92: 0 | L92: 0 | M92: 10K031 | N92: KOLKATRIOL KAP 0.25 MCG | O92: KOLKATRIOL KAP 0.25 MCG | P92: OBAT PADAT (PERSEDIAAN LAINNYA)
A93: 1010401002 | B93: 000329 | C93: 1 | D93: 1 | E93: 3710 | F93: 0 | G93: 0 | K93: 0 | L93: 0 | M93: 10K044 | N93: KLOROKUIN TABLET 150 MG (SULFAT) | O93: KLOROKUIN TABLET 150 MG (SULFAT) | P93: OBAT PADAT (PERSEDIAAN LAINNYA)
A94: 1010401002 | B94: 000493 | C94: 1 | D94: 1 | E94: 0 | F94: 0 | G94: 0 | K94: 0 | L94: 0 | M94: 10K055 | N94: KEPPRA FC TABLET 250 MG | O94: KEPPRA FC TABLET 250 MG | P94: OBAT PADAT (PERSEDIAAN LAINNYA)
A95: 1010401002 | B95: 000020 | C95: 1 | D95: 1 | E95: 335 | F95: 0 | G95: 0 | K95: 0 | L95: 0 | M95: 10K067 | N95: KALXETIN CAP 10 MG | O95: KALXETIN CAP 10 MG | P95: OBAT PADAT (PERSEDIAAN LAINNYA)
A96: 1010401002 | B96: 000010 | C96: 1 | D96: 1 | E96: 150 | F96: 0 | G96: 0 | K96: 0 | L96: 0 | M96: 10K071 | N96: KETESSE TAB 25 MG | O96: KETESSE TAB 25 MG | P96: OBAT PADAT (PERSEDIAAN LAINNYA)
A97: 1010401002 | B97: 000326 | C97: 1 | D97: 1 | E97: 51 | F97: 0 | G97: 0 | K97: 0 | L97: 0 | M97: 10K074 | N97: KETRICIN TAB 4 MG | O97: KETRICIN TAB 4 MG | P97: OBAT PADAT (PERSEDIAAN LAINNYA)
A98: 1010401999 | B98: 003513 | C98: 1 | D98: 1 | E98: 126 | F98: 0 | G98: 0 | K98: 0 | L98: 0 | M98: 10K109 | N98: KALOBA CAPSUL | O98: KALOBA CAPSUL | P98: OBAT LAINNYA (PERSEDIAAN LAINNYA)
A99: 1010401999 | B99: 003512 | C99: 1 | D99: 1 | E99: 6122 | F99: 0 | G99: 31 | H99: 31 | I99: 31 | J99: 0 | K99: 0 | L99: 0 | M99: 10K109.01 | N99: KETOPROFEN 100 MG TAB | O99: KETOPROFEN 100 MG TAB | P99: OBAT LAINNYA (PERSEDIAAN LAINNYA)
A100: 1010401002 | B100: 000312 | C100: 1 | D100: 1 | E100: 20 | F100: 0 | G100: 0 | K100: 0 | L100: 0 | M100: 10L115 | N100: LANCID KAPSUL 30 MG | O100: LANCID KAPSUL 30 MG | P100: OBAT PADAT (PERSEDIAAN LAINNYA)
...

Sheet selisihPlus
A1: sakti_kode_klp | B1: sakti_kode | C1: katalog_grp | D1: sakti_grp | E1: qty_awal | F1: sakti_awal_add | G1: sakti_akhir | H1: simrs_akhir | I1: pembulatan | J1: simrs_trx | K1: selisih_abs | L1: selisih | M1: katalog_kode | N1: katalog_nama | O1: sakti_nama | P1: sakti_nama_klp
A2: 1010401002 | B2: 000478 | C2: 1 | D2: 1 | E2: 17589 | F2: 0 | G2: 5887 | H2: 9490 | I2: 9490 | J2: 3603 | K2: 3603 | L2: 3603 | M2: 10A025 | N2: ADALAT OROS TAB 30 MG | O2: ADALAT OROS TAB 30 MG | P2: OBAT PADAT (PERSEDIAAN LAINNYA)
A3: 1010401999 | B3: 000351 | C3: 2 | D3: 2 | E3: 142889 | F3: 0 | G3: 0 | H3: 10279 | I3: 10279 | J3: 10279 | K3: 10279 | L3: 10279 | M3: 10A254 | N3: ACETYLCYSTEIN 200 MG CAPSUL | O3: ACETYLCYSTEIN 200 MG CAPSUL | P3: OBAT PADAT (PERSEDIAAN LAINNYA)
A4: 1010401002 | B4: 000454 | C4: 1 | D4: 1 | E4: 23983 | F4: 0 | G4: 11421 | H4: 20516 | I4: 20516 | J4: 9095 | K4: 9095 | L4: 9095 | M4: 10A258 | N4: ACARBOSE TABLET 100 MG | O4: ACARBOSE TABLET 100 MG | P4: OBAT PADAT (PERSEDIAAN LAINNYA)
A5: 1010401002 | B5: 000453 | C5: 1 | D5: 1 | E5: 6364 | F5: 0 | G5: 3709 | H5: 6414 | I5: 6414 | J5: 2705 | K5: 2705 | L5: 2705 | M5: 10A259 | N5: ACARBOSE TAB 50 MG | O5: ACARBOSE TAB 50 MG | P5: OBAT PADAT (PERSEDIAAN LAINNYA)
A6: 1010401999 | B6: 003565 | C6: 2 | D6: 2 | E6: 6409 | F6: 0 | G6: 355 | H6: 680 | I6: 680 | J6: 325 | K6: 325 | L6: 325 | M6: 10A300 | N6: AMOXICILLIN TRIHYDRATE KAPLET 500 MG | O6: AMOXSAN CAP 500 MG | P6: OBAT PADAT (PERSEDIAAN LAINNYA)
A7: 1010401999 | B7: 001068 | C7: 2 | D7: 2 | E7: 36185 | F7: 0 | G7: 23959 | H7: 28975 | I7: 28975 | J7: 10865 | K7: 5016 | L7: 5016 | M7: 10B132 | N7: BISOPROLOL TABLET 5 MG | O7: BISOPROLOL TABLET 5 MG | P7: OBAT PADAT (PERSEDIAAN LAINNYA)
A8: 1010401999 | B8: 003560 | C8: 2 | D8: 2 | E8: 6896 | F8: 0 | G8: 776 | H8: 4234 | I8: 4234 | J8: 3378 | K8: 3458 | L8: 3458 | M8: 10B135 | N8: BETAHISTIN MESILAT TABLET 6 MG (DEXA) | O8: BETAHISTIN TABLET 6 MG | P8: OBAT PADAT (PERSEDIAAN LAINNYA)
A9: 1010401999 | B9: 001166 | C9: 1 | D9: 1 | E9: 38149 | F9: 0 | G9: 7686 | H9: 25625 | I9: 25625 | J9: 18628 | K9: 17939 | L9: 17939 | M9: 10B141 | N9: BISOPROLOL TABLET 2,5MG | O9: BISOPROLOL TABLET 2,5MG | P9: OBAT LAINNYA (PERSEDIAAN LAINNYA)
A10: 1010401999 | B10: 003556 | C10: 1 | D10: 1 | E10: 1060 | F10: 0 | G10: 989 | H10: 1417.5 | I10: 1418 | J10: 428.5 | K10: 428.5 | L10: 428.5 | M10: 10C001.002 | N10: CLOZAPINE TABLET 25 MG | O10: CLOZAPINE TABLET 25 MG | P10: OBAT LAINNYA (PERSEDIAAN LAINNYA)
A11: 1010401999 | B11: 003555 | C11: 1 | D11: 1 | E11: 11249 | F11: 0 | G11: 1948 | H11: 3688 | I11: 3688 | J11: 1740 | K11: 1740 | L11: 1740 | M11: 10C001.003 | N11: CIPROFLOXACIN TABLET 500 MG | O11: CIPROFLOXACIN TABLET 500 MG | P11: OBAT LAINNYA (PERSEDIAAN LAINNYA)
A12: 1010401002 | B12: 000434 | C12: 1 | D12: 1 | E12: 3814 | F12: 0 | G12: 13355 | H12: 16022.5 | I12: 16023 | J12: 1187.5 | K12: 2667.5 | L12: 2667.5 | M12: 10C001.023 | N12: CEFIXIME CAP 100 MG | O12: CEFIXIME CAP 100 MG | P12: OBAT PADAT (PERSEDIAAN LAINNYA)
A13: 1010401002 | B13: 000423 | C13: 1 | D13: 1 | E13: 1493 | F13: 0 | G13: 316 | H13: 621 | I13: 621 | J13: 305 | K13: 305 | L13: 305 | M13: 10C001.094 | N13: CRIPSA TAB 2.5 MG | O13: CRIPSA TAB 2.5 MG | P13: OBAT PADAT (PERSEDIAAN LAINNYA)
... A18: 1010401999 | B18: 003543 | C18: 1 | D18: 1 | E18: 5208 | F18: 0 | G18: 4913 | H18: 5024 | I18: 5024 | J18: 0 | K18: 111 | L18: 111 | M18: 10C125 | N18: OSELTAMIVIR TABLET (COVID-19) | O18: OSELTAMIVIR TABLET (COVID-19) | P18: OBAT LAINNYA (PERSEDIAAN LAINNYA)
A19: 1010401999 | B19: 001045 | C19: 3 | D19: 3 | E19: 6242 | F19: 0 | G19: 14 | H19: 112 | I19: 112 | J19: 112 | K19: 98 | L19: 98 | M19: 10D091 | O19: DONPERIDON TAB 10 MG | P19: OBAT PADAT (PERSEDIAAN LAINNYA)
A20: 1010401002 | B20: 000387 | C20: 1 | D20: 1 | E20: 1836 | F20: 0 | G20: 781 | H20: 4593 | I20: 4593 | J20: 3812 | K20: 3812 | L20: 3812 | M20: 10D178 | N20: DEXKETOPROFEN TAB | O20: DEXKETOPROFEN TAB | P20: OBAT PADAT (PERSEDIAAN LAINNYA)
A21: 1010401999 | B21: 000991 | C21: 1 | D21: 1 | E21: 1373 | F21: 0 | G21: 944 | H21: 2375.5 | I21: 2376 | J21: 1432.25 | K21: 1431.5 | L21: 1431.5 | M21: 10D193 | N21: DIAZEPAM TABLET 2 MG | O21: DIAZEPAM TABLET 2 MG | P21: OBAT LAINNYA (PERSEDIAAN LAINNYA)
A22: 1010401999 | B22: 001164 | C22: 1 | D22: 1 | E22: 8105 | F22: 0 | G22: 32 | H22: 12320 | I22: 12320 | J22: 12282 | K22: 12288 | L22: 12288 | M22: 10D199.2 | N22: DIVALPROEX SODIUM KAPLET LEPAS LAMBAT 250MG | O22: DIVALPROEX SODIUM KAPLET LEPAS LAMBAT 250MG | P22: OBAT LAINNYA (PERSEDIAAN LAINNYA)
A23: 1010401999 | B23: 001067 | C23: 1 | D23: 1 | E23: 9008 | F23: 0 | G23: 385 | H23: 8785 | I23: 8785 | J23: 8400 | K23: 8400 | L23: 8400 | M23: 10D200 | N23: DIVALPROEX SODIUM KAPLET LEPAS LAMBAT 500MG | O23: DIVALPROEX SODIUM KAPLET LEPAS LAMBAT 500MG | P23: OBAT LAINNYA (PERSEDIAAN LAINNYA)
A24: 1010401002 | B24: 000384 | C24: 1 | D24: 1 | E24: 100 | F24: 0 | G24: 136 | H24: 229 | I24: 229 | J24: 93 | K24: 93 | L24: 93 | M24: 10E041 | N24: ESILGAN TABLET 1 mg | O24: ESILGAN TABLET 1 mg | P24: OBAT PADAT (PERSEDIAAN LAINNYA)
A25: 1010401002 | B25: 000382 | C25: 1 | D25: 1 | E25: 465 | F25: 0 | G25: 46 | H25: 74 | I25: 74 | J25: 28 | K25: 28 | L25: 28 | M25: 10E081 | N25: ERGOTAMIN COFFEINE | O25: ERGOTAMIN COFFEINE | P25: OBAT PADAT (PERSEDIAAN LAINNYA)
A26: 1010401999 | B26: 001143 | C26: 1 | D26: 1 | E26: 3440 | F26: 0 | G26: 500 | H26: 637.5 | I26: 638 | J26: 137.5 | K26: 137.5 | L26: 137.5 | M26: 10F159 | N26: FLUOXETINE HCL TAB 20MG | O26: FLUOXETINE HCL TAB 20MG | P26: OBAT LAINNYA (PERSEDIAAN LAINNYA)
A27: 1010401999 | B27: 001098 | C27: 1 | D27: 1 | E27: 2122 | F27: 0 | G27: 3032 | H27: 4927 | I27: 4927 | J27: 1895 | K27: 1895 | L27: 1895 | M27: 10F160 | N27: FONYLIN MR 60MG | O27: FONYLIN MR 60MG | P27: OBAT LAINNYA (PERSEDIAAN LAINNYA)
A28: 1010401999 | B28: 000679 | C28: 1 | D28: 1 | E28: 117 | F28: 0 | G28: 634 | H28: 1371 | I28: 1371 | J28: 737 | K28: 737 | L28: 737 | M28: 10F161 | N28: FENOFIBRAT CAPS 100MG | O28: FENOFIBRAT CAPS 100MG | P28: OBAT LAINNYA (PERSEDIAAN LAINNYA)
A29: 1010401002 | B29: 000361 | C29: 1 | D29: 1 | E29: 8685 | F29: 0 | G29: 1784 | H29: 8354.5 | I29: 8355 | J29: 6570.5 | K29: 6570.5 | L29: 6570.5 | M29: 10G081 | N29: GLIQUIDONE TABLET 30 MG | O29: GLIQUIDONE TABLET 30 MG | P29: OBAT PADAT (PERSEDIAAN LAINNYA)
A30: 1010401999 | B30: 003528 | C30: 2 | D30: 2 | E30: 10695 | F30: 0 | G30: 1088 | H30: 2224 | I30: 2224 | J30: 1136 | K30: 1136 | L30: 1136 | M30: 10G123 | N30: GLIMEPIRIDE TAB 1MG | O30: GLIMEPIRIDE TAB 1MG | P30: OBAT PADAT (PERSEDIAAN LAINNYA)
A31: 1010401999 | B31: 001019 | C31: 1 | D31: 1 | E31: 15402 | F31: 0 | G31: 1187 | H31: 6399 | I31: 6399 | J31: 5026 | K31: 5212 | L31: 5212 | M31: 10G132 | N31: GABAPENTIN KAPSUL 300MG | O31: GABAPENTIN KAPSUL 300MG | P31: OBAT LAINNYA (PERSEDIAAN LAINNYA)
... A261: 1010401999 | B261: 004232 | C261: 1 | D261: 1 | E261: 0 | F261: 0 | G261: 0 | H261: 1 | I261: 1 | J261: 1 | K261: 1 | L261: 1 | M261: 42M329 | N261: MATA BOR CUTTING ULTRA 5PK 3MM LONG (31313069U) | O261: MATA BOR CUTTING ULTRA 5PK 3MM LONG (31313069U) | P261: OBAT LAINNYA (PERSEDIAAN LAINNYA)
A262: 1010401999 | B262: 004234 | C262: 1 | D262: 1 | E262: 0 | F262: 0 | G262: 1 | H262: 4 | I262: 4 | J262: 3 | K262: 3 | L262: 3 | M262: 42M339 | O262: MATA BOR CUTTING ULTRA 5PK 5MM LONG (31315066U) | P262: OBAT LAINNYA (PERSEDIAAN LAINNYA)
A263: 1010401999 | B263: 004236 | C263: 1 | D263: 1 | E263: 0 | F263: 0 | G263: 2 | H263: 4.6 | I263: 5 | J263: 2.6 | K263: 2.6 | L263: 2.6 | M263: 42M340 | O263: MATA BOR DIAMOND 2MM FINE (31132070) | P263: OBAT LAINNYA (PERSEDIAAN LAINNYA)
A264: 1010401999 | B264: 004237 | C264: 1 | D264: 1 | E264: 0 | F264: 0 | G264: 4 | H264: 7.2 | I264: 8 | J264: 3.2 | K264: 3.2 | L264: 3.2 | M264: 42M341 | N264: MATA BOR DIAMOND 4MM FINE LONG (31134068) | O264: MATA BOR DIAMOND 4MM FINE LONG (31134068) | P264: OBAT LAINNYA (PERSEDIAAN LAINNYA)
A265: 1010401999 | B265: 004245 | C265: 1 | D265: 1 | E265: 0 | F265: 0 | G265: 0 | H265: 2 | I265: 2 | J265: 2 | K265: 2 | L265: 2 | M265: 42N077 | N265: NAIL SCREW | O265: NOVOSIS | P265: OBAT LAINNYA (PERSEDIAAN LAINNYA)
A266: 1010401999 | B266: 000086 | C266: 1 | D266: 1 | E266: 0 | F266: 0 | G266: 0 | H266: 1 | I266: 1 | J266: 1 | K266: 1 | L266: 1 | M266: 42N124 | N266: NEOGEN LOCKING SCREW 4.5 X 26-90 MM | O266: NEOGEN LOCKING SCREW 4.5 X 26-90 MM | P266: OBAT LAINNYA (PERSEDIAAN LAINNYA)
A267: 1010401006 | B267: 000043 | C267: 1 | D267: 1 | E267: 0 | F267: 0 | G267: 0 | H267: 2 | I267: 2 | J267: 2 | K267: 2 | L267: 2 | M267: 42P233 | N267: PARCUS BRAID V-LOX PEEK CF SUTURE ANCHOR 10324T | O267: PARCUS BRAID V-LOX PEEK CF SUTURE ANCHOR 10324T | P267: ALAT/ OBAT KONTRASEPSI KELUARGA BERENCANA(PERSEDIAAN LAINNYA)
A268: 1010401999 | B268: 002991 | C268: 1 | D268: 1 | E268: 0 | F268: 0 | G268: 0 | H268: 1 | I268: 1 | J268: 1 | K268: 1 | L268: 1 | M268: 42P339 | N268: PROXIMAL TIBIAL ├â╦£4.5/5.0 LCP 4-10 HOLE Ti L/R | O268: PROXIMAL TIBIAL ├ÿ4.5/5.0 LCP 4-10 HOLE Ti L/R | P268: OBAT LAINNYA (PERSEDIAAN LAINNYA)
A269: 1010401999 | B269: 002989 | C269: 1 | D269: 1 | E269: 0 | F269: 0 | G269: 1 | H269: 5 | I269: 5 | J269: 4 | K269: 4 | L269: 4 | M269: 42P344 | N269: PHILOS | O269: PHILOS | P269: OBAT LAINNYA (PERSEDIAAN LAINNYA)
A270: 1010401999 | B270: 002987 | C270: 1 | D270: 1 | E270: 0 | F270: 0 | G270: 2 | H270: 6 | I270: 6 | J270: 4 | K270: 4 | L270: 4 | M270: 42P359 | N270: PFNA-II NAIL | O270: PFNA-II NAIL | P270: OBAT LAINNYA (PERSEDIAAN LAINNYA)
A271: 1010401999 | B271: 002986 | C271: 1 | D271: 1 | E271: 0 | F271: 0 | G271: 2 | H271: 6 | I271: 6 | J271: 4 | K271: 4 | L271: 4 | M271: 42P360 | N271: PFNA-II BLADE | O271: PFNA-II BLADE | P271: OBAT LAINNYA (PERSEDIAAN LAINNYA)
A272: 1010401999 | B272: 002985 | C272: 1 | D272: 1 | E272: 0 | F272: 0 | G272: 2 | H272: 5 | I272: 5 | J272: 3 | K272: 3 | L272: 3 | M272: 42P361 | N272: PFNA-II END CAP | O272: PFNA-II END CAP | P272: OBAT LAINNYA (PERSEDIAAN LAINNYA)
A273: 1010401999 | B273: 002984 | C273: 1 | D273: 1 | E273: 0 | F273: 0 | G273: 5 | H273: 40 | I273: 40 | J273: 35 | K273: 35 | L273: 35 | M273: 42P362 | N273: PFNA-II - A2FN - ETN - 5.0 LOCKING SCREWS | O273: PFNA-II - A2FN - ETN - 5.0 LOCKING SCREWS | P273: OBAT LAINNYA (PERSEDIAAN LAINNYA)
A274: 1010401999 | B274: 001858 | C274: 1 | D274: 1 | E274: 0 | F274: 0 | G274: 0 | H274: 3 | I274: 3 | J274: 3 | K274: 3 | L274: 3 | M274: 42P367 | N274: PAKET ACL ARTHROSCOPY | O274: PAKET ACL ARTHROSCOPY | P274: OBAT LAINNYA (PERSEDIAAN LAINNYA)
A275: 1010401999 | B275: 003733 | C275: 1 | D275: 1 | E275: 0 | F275: 0 | G275: 0 | H275: 1 | I275: 1 | J275: 1 | K275: 1 | L275: 1 | M275: 42R282 | N275: RECONSTRUCTION LOCKING PLATE 2.7 X 7-17H | O275: RECONSTRUCTION LOCKING PLATE 2.7 X 7-17H | P275: OBAT LAINNYA (PERSEDIAAN LAINNYA)
... A309: 1010401999 | B309: 002906 | C309: 1 | D309: 1 | E309: 0 | F309: 0 | G309: 6 | H309: 6.4 | I309: 7 | J309: 0 | K309: 0.4 | L309: 0.4 | M309: 80C001.113 | N309: CVS ANTPAK 0.9 W/O PROBE-PHACOPAK | O309: CVS ANTPAK 0.9 W/O PROBE-PHACOPAK | P309: OBAT LAINNYA (PERSEDIAAN LAINNYA)
A310: 1010401999 | B310: 004156 | C310: 1 | D310: 1 | E310: 0 | F310: 0 | G310: 0 | H310: 3 | I310: 3 | J310: 3 | K310: 3 | L310: 3 | M310: 80C005.1 | O310: COLOSTOMY BAG FREE | P310: OBAT LAINNYA (PERSEDIAAN LAINNYA)
A311: 1010401999 | B311: 000131 | C311: 1 | D311: 2 | E311: 1000 | F311: 0 | G311: 485 | H311: 512 | I311: 512 | J311: 57 | K311: 27 | L311: 27 | M311: 80C007 | N311: CHROMA FOLEY CATHETER 2 WAY CH 16 | O311: CHROMA FOLEY CATHETER 2 WAY CH 16 | P311: OBAT LAINNYA (PERSEDIAAN LAINNYA)
A312: 1010401999 | B312: 000130 | C312: 1 | D312: 2 | E312: 180 | F312: 0 | G312: 264 | H312: 318 | I312: 318 | J312: 54 | K312: 54 | L312: 54 | M312: 80C008 | N312: CHROMA FOLEY CATHETER 2 WAY CH 18 | O312: CHROMA FOLEY CATHETER 2 WAY CH 18 | P312: OBAT LAINNYA (PERSEDIAAN LAINNYA)
A313: 1010401999 | B313: 004025 | C313: 1 | D313: 1 | E313: 0 | F313: 0 | G313: 135 | H313: 153 | I313: 153 | J313: 18 | K313: 18 | L313: 18 | M313: 80C038 | N313: CHROMA FOLEY CATHETER 2 WAY CH 14 | O313: CHROMA FOLEY CATHETER 2 WAY CH 14 | P313: OBAT LAINNYA (PERSEDIAAN LAINNYA)
A314: 1010401006 | B314: 000801 | C314: 1 | D314: 1 | E314: 11 | F314: 0 | G314: 0 | H314: 3 | I314: 3 | J314: 3 | K314: 3 | L314: 3 | M314: 80C065 | N314: CYSTOFIX F10, 8 CM | O314: CYSTOFIX F10, 8 CM | P314: ALAT/ OBAT KONTRASEPSI KELUARGA BERENCANA(PERSEDIAAN LAINNYA)
A315: 1010401006 | B315: 000790 | C315: 1 | D315: 1 | E315: 23 | F315: 0 | G315: 36 | H315: 41 | I315: 41 | J315: 5 | K315: 5 | L315: 5 | M315: 80D129 | N315: DISP.SYRINJECTOR 120FLOW (ISJ12-P0510-EU) | O315: DISP.SYRINJECTOR 120FLOW (ISJ12-P0510-EU) | P315: ALAT/ OBAT KONTRASEPSI KELUARGA BERENCANA(PERSEDIAAN LAINNYA)
A316: 1010401999 | B316: 000337 | C316: 1 | D316: 1 | E316: 1365 | F316: 0 | G316: 2084 | H316: 2682 | I316: 2682 | J316: 598 | K316: 598 | L316: 598 | M316: 80D167.1 | N316: DOUBLE SPIKE | O316: DOUBLE SPIKE | P316: OBAT LAINNYA (PERSEDIAAN LAINNYA)
A317: 1010401006 | B317: 000777 | C317: 1 | D317: 2 | E317: 37 | F317: 0 | G317: 15 | H317: 31 | I317: 31 | J317: -4 | K317: 16 | L317: 16 | M317: 80E016 | N317: ENDOTRACHEAL CLEAR PROF S.S 5 CUFF | O317: ENDOTRACHEAL CLEAR PROF S.S 5 CUFF | P317: OBAT LAINNYA (PERSEDIAAN LAINNYA)
A318: 1010401006 | B318: 000776 | C318: 1 | D318: 1 | E318: 0 | F318: 4 | G318: 2 | H318: 23 | I318: 23 | J318: -3 | K318: 21 | L318: 21 | M318: 80E017 | N318: ENDOTRACHEAL CLEAR PROF S.S 6 CUFF | O318: ENDOTRACHEAL CLEAR PROF S.S 6 CUFF | P318: Alat/Obat Kontrasepsi Keluarga Berencana(Persediaan Lainnya)
A319: 1010401006 | B319: 000768 | C319: 1 | D319: 2 | E319: 25 | F319: 0 | G319: 2 | H319: 18 | I319: 18 | J319: -4 | K319: 16 | L319: 16 | M319: 80E058 | N319: ENDOTRACHEAL CLEAR PROF S.S 6,5 CUFF | O319: ENDOTRACHEAL CLEAR PROF S.S 6,5 CUFF | P319: OBAT LAINNYA (PERSEDIAAN LAINNYA)
A320: 1010401999 | B320: 001462 | C320: 1 | D320: 1 | E320: 1 | F320: 0 | G320: 2 | H320: 5 | I320: 5 | J320: 3 | K320: 3 | L320: 3 | M320: 80E146 | N320: ENDOVENOUS LASER ABLATION (EVLT) | O320: ENDOVENOUS LASER ABLATION (EVLT) | P320: OBAT LAINNYA (PERSEDIAAN LAINNYA)
A321: 1010401999 | B321: 002867 | C321: 1 | D321: 1 | E321: 10 | F321: 0 | G321: 4 | H321: 7 | I321: 7 | J321: 3 | K321: 3 | L321: 3 | M321: 80E149 | N321: EPILONG KIT TOUHY NEEDLE 18GX90MM | O321: EPILONG KIT TOUHY NEEDLE 18GX90MM | P321: OBAT LAINNYA (PERSEDIAAN LAINNYA)
A322: 1010401999 | B322: 004134 | C322: 1 | D322: 1 | E322: 0 | F322: 0 | G322: 0 | H322: 6 | I322: 6 | J322: 0 | K322: 6 | L322: 6 | M322: 80F118 | N322: FOLEY CATHETER SILICONE 14 FR | O322: FOLEY CATH SILICON NO.14 | P322: OBAT LAINNYA (PERSEDIAAN LAINNYA)
... A350: 1010401999 | B350: 003925 | C350: 1 | D350: 1 | E350: 0 | F350: 0 | G350: 6 | H350: 15 | I350: 15 | J350: 9 | K350: 9 | L350: 9 | M350: 80P199 | N350: PRESSURE TRANSDUCER KIT DTX PLUS (2606225) | O350: PRESSURE TRANSDUCER KIT DTX PLUS (2606225) | P350: OBAT LAINNYA (PERSEDIAAN LAINNYA)
A351: 1010401999 | B351: 004258 | C351: 1 | D351: 1 | E351: 0 | F351: 0 | G351: 0 | H351: 6 | I351: 6 | J351: -4 | K351: 6 | L351: 6 | M351: 80P210 | O351: PARIETEN MACROPORUS MESH PPM 15X10 (PPM1510) | P351: OBAT LAINNYA (PERSEDIAAN LAINNYA)
A352: 1010401006 | B352: 000565 | C352: 1 | D352: 1 | E352: 1 | F352: 0 | G352: 0 | H352: 2 | I352: 2 | J352: 0 | K352: 2 | L352: 2 | M352: 80R043 | N352: REINFORCED TRACHEAL CUFF 4 | O352: REINFORCED TRACHEAL CUFF 4 | P352: ALAT/ OBAT KONTRASEPSI KELUARGA BERENCANA(PERSEDIAAN LAINNYA)
A353: 1010401999 | B353: 002697 | C353: 1 | D353: 1 | E353: 4 | F353: 0 | G353: 20 | H353: 25 | I353: 25 | J353: 5 | K353: 5 | L353: 5 | M353: 80R075 | N353: RENOVISION NEPHROSTOMY KIT 7FR/8FR | O353: RENOVISION NEPHROSTOMY KIT 7FR/8FR | P353: OBAT LAINNYA (PERSEDIAAN LAINNYA)
A354: 1010401999 | B354: 004031 | C354: 1 | D354: 1 | E354: 0 | F354: 0 | G354: 0 | H354: 261 | I354: 261 | J354: -74 | K354: 261 | L354: 261 | M354: 80S023 | N354: SPINAL NEEDLE QUENCKE 27G | O354: SPINAL NEEDLE QUENCKE 27G | P354: OBAT LAINNYA (PERSEDIAAN LAINNYA)
A355: 1010401006 | B355: 000535 | C355: 1 | D355: 1 | E355: 52 | F355: 0 | G355: 0 | H355: 411 | I355: 411 | J355: -90 | K355: 411 | L355: 411 | M355: 80S124 | N355: SUCTION CATHETER CH 8 | O355: SUCTION CATHETER CH 8 | P355: ALAT/ OBAT KONTRASEPSI KELUARGA BERENCANA(PERSEDIAAN LAINNYA)
A356: 1010401006 | B356: 000529 | C356: 1 | D356: 1 | E356: 935 | F356: 0 | G356: 294 | H356: 930 | I356: 930 | J356: 636 | K356: 636 | L356: 636 | M356: 80S168 | N356: SURGICAL CONNECTING TUBE 2 FUNNEL | O356: SURGICAL CONNECTING TUBE 2 FUNNEL | P356: ALAT/ OBAT KONTRASEPSI KELUARGA BERENCANA(PERSEDIAAN LAINNYA)
A357: 1010401999 | B357: 004081 | C357: 1 | D357: 1 | E357: 0 | F357: 0 | G357: 111 | H357: 210 | I357: 210 | J357: 99 | K357: 99 | L357: 99 | M357: 80S168.3 | N357: SUCTION YANKAUER TIP | O357: SUCTION YANKAUER TIP | P357: OBAT LAINNYA (PERSEDIAAN LAINNYA)
A358: 1010401999 | B358: 004158 | C358: 1 | D358: 1 | E358: 0 | F358: 0 | G358: 0 | H358: 50 | I358: 50 | J358: 50 | K358: 50 | L358: 50 | M358: 80S173 | N358: SURGICAL GLOVE STERIL ORTHOPAEDIC NO. 7,5 | O358: SURGICAL GLOVE STERIL ORTHOPAEDIC NO. 7,5 | P358: OBAT LAINNYA (PERSEDIAAN LAINNYA)
A359: 1010401006 | B359: 000522 | C359: 1 | D359: 1 | E359: 53 | F359: 0 | G359: 30 | H359: 67 | I359: 67 | J359: 37 | K359: 37 | L359: 37 | M359: 80S223 | N359: SYRINJECTOR 120 FLOW (ISJ12-P2040-EU) | O359: SYRINJECTOR 120 FLOW (ISJ12-P2040-EU) | P359: ALAT/ OBAT KONTRASEPSI KELUARGA BERENCANA(PERSEDIAAN LAINNYA)
A360: 1010401006 | B360: 000520 | C360: 1 | D360: 1 | E360: 40 | F360: 0 | G360: 0 | H360: 7 | I360: 7 | J360: 7 | K360: 7 | L360: 7 | M360: 80S238 | N360: STERRAD 100S CASSETTE (10113) | O360: STERRAD 100S CASSETTE (10113) | P360: ALAT/ OBAT KONTRASEPSI KELUARGA BERENCANA(PERSEDIAAN LAINNYA)
A361: 1010401999 | B361: 002676 | C361: 1 | D361: 1 | E361: 50 | F361: 0 | G361: 24 | H361: 33 | I361: 33 | J361: 9 | K361: 9 | L361: 9 | M361: 80S291 | N361: SONOPLEX STIM CANNULA 22G X 50 MM (1185-74) | O361: SONOPLEX STIM CANNULA 22G X 50 MM (1185-74) | P361: OBAT LAINNYA (PERSEDIAAN LAINNYA)
A362: 1010401999 | B362: 002675 | C362: 1 | D362: 1 | E362: 76 | F362: 0 | G362: 56 | H362: 68 | I362: 68 | J362: 12 | K362: 12 | L362: 12 | M362: 80S292 | N362: SONOPLEX STIM CANNULA 21G X 100 MM (1185-77) | O362: SONOPLEX STIM CANNULA 21G X 100 MM (1185-77) | P362: OBAT LAINNYA (PERSEDIAAN LAINNYA)
A363: 1010401999 | B363: 003777 | C363: 1 | D363: 1 | E363: 0 | F363: 0 | G363: 1646 | H363: 3656 | I363: 3656 | J363: 1987 | K363: 2010 | L363: 2010 | M363: 80V026 | N363: VENFLON PRO SAFETY IV CANNULA 20G | O363: VENFLON PRO SAFETY IV CANNULA 20G | P363: OBAT LAINNYA (PERSEDIAAN LAINNYA)
... A394: 1010401001 | B394: 000145 | C394: 1 | D394: 1 | E394: 0 | F394: 0 | G394: 0 | H394: 10 | I394: 10 | J394: 10 | K394: 10 | L394: 10 | M394: PFL002 | N394: LYSOL 1:5 L | O394: LYSOL 1:5 L | P394: OBAT CAIR (PERSEDIAAN LAINNYA)
E395: =SUM(E2:E394) -> 1639516 | F395: =SUM(F2:F394) -> 406 | G395: =SUM(G2:G394) -> 500514 | H395: =SUM(H2:H394) -> 1127270.8 | I395: =SUM(I2:I394) -> 1127284
